{"prefix": {"xsd_1": "http://www.w3.org/2000/10/XMLSchema#", "prov-ml": "prov-ml", "default": "www.example.org"}, "entity": {"MetricsType.ZARR_False_zstd": [{"prov-ml:provenance_path": "prov", "prov-ml:artifact_uri": "prov/MetricsType.ZARR_False_zstd_0/artifacts", "prov-ml:run_id": "0", "prov-ml:type": "LearningStage", "prov-ml:user_id": "gabriele.padovani", "prov-ml:python_version": "3.11.11 (main, Dec 11 2024, 16:28:39) [GCC 11.2.0]", "prov-ml:global_rank": "0"}, {"prov-ml:type": "Experiment", "prov-ml:experiment_name": "MetricsType.ZARR_False_zstd"}], "source_code": {"prov-ml:type": "SourceCode", "prov-ml:source_name": "provenance_graph.py", "prov-ml:runtime_type": "single_core"}, "MSE_train_Context.TRAINING": {"prov-ml:type": "Metric", "prov-ml:name": "MSE_train", "prov-ml:context": "Context.TRAINING", "prov-ml:source": "custom_metric", "prov-ml:metric_epoch_list": "[0, 0, 0, ..., 4, 4, 4]", "prov-ml:metric_value_list": "[0.13026315, 0.1185761 , 0.11206033, ..., 0.07822614, 0.06727719, 0.07177756]", "prov-ml:metric_timestamp_list": "[1749039885844, 1749039885850, 1749039885856, ..., 1749039976155, 1749039976160, 1749039976166]", "prov-ml:artifact_uri": "prov/MetricsType.ZARR_False_zstd_0/artifacts/metrics/MSE_train_Context.TRAINING_GR0.zarr"}, "MSE_train2_Context.TRAINING": {"prov-ml:type": "Metric", "prov-ml:name": "MSE_train2", "prov-ml:context": "Context.TRAINING", "prov-ml:source": "custom_metric", "prov-ml:metric_epoch_list": "[0, 0, 0, ..., 4, 4, 4]", "prov-ml:metric_value_list": "[1.1302631, 1.118576 , 1.1120603, ..., 1.0782261, 1.0672772, 1.0717776]", "prov-ml:metric_timestamp_list": "[1749039885844, 1749039885850, 1749039885856, ..., 1749039976155, 1749039976160, 1749039976166]", "prov-ml:artifact_uri": "prov/MetricsType.ZARR_False_zstd_0/artifacts/metrics/MSE_train2_Context.TRAINING_GR0.zarr"}, "MSE_train3_Context.TRAINING": {"prov-ml:type": "Metric", "prov-ml:name": "MSE_train3", "prov-ml:context": "Context.TRAINING", "prov-ml:source": "custom_metric", "prov-ml:metric_epoch_list": "[0, 0, 0, ..., 4, 4, 4]", "prov-ml:metric_value_list": "[2.130263 , 2.118576 , 2.1120603, ..., 2.078226 , 2.0672772, 2.0717776]", "prov-ml:metric_timestamp_list": "[1749039885844, 1749039885850, 1749039885856, ..., 1749039976155, 1749039976160, 1749039976166]", "prov-ml:artifact_uri": "prov/MetricsType.ZARR_False_zstd_0/artifacts/metrics/MSE_train3_Context.TRAINING_GR0.zarr"}, "MSE_train4_Context.TRAINING": {"prov-ml:type": "Metric", "prov-ml:name": "MSE_train4", "prov-ml:context": "Context.TRAINING", "prov-ml:source": "custom_metric", "prov-ml:metric_epoch_list": "[0, 0, 0, ..., 4, 4, 4]", "prov-ml:metric_value_list": "[3.130263 , 3.118576 , 3.1120603, ..., 3.078226 , 3.0672772, 3.0717776]", "prov-ml:metric_timestamp_list": "[1749039885844, 1749039885850, 1749039885856, ..., 1749039976155, 1749039976160, 1749039976166]", "prov-ml:artifact_uri": "prov/MetricsType.ZARR_False_zstd_0/artifacts/metrics/MSE_train4_Context.TRAINING_GR0.zarr"}, "MSE_train5_Context.TRAINING": {"prov-ml:type": "Metric", "prov-ml:name": "MSE_train5", "prov-ml:context": "Context.TRAINING", "prov-ml:source": "custom_metric", "prov-ml:metric_epoch_list": "[0, 0, 0, ..., 4, 4, 4]", "prov-ml:metric_value_list": "[4.1302633, 4.118576 , 4.1120605, ..., 4.078226 , 4.067277 , 4.0717773]", "prov-ml:metric_timestamp_list": "[1749039885844, 1749039885850, 1749039885856, ..., 1749039976155, 1749039976160, 1749039976166]", "prov-ml:artifact_uri": "prov/MetricsType.ZARR_False_zstd_0/artifacts/metrics/MSE_train5_Context.TRAINING_GR0.zarr"}, "Indices_Context.TRAINING": {"prov-ml:type": "Metric", "prov-ml:name": "Indices", "prov-ml:context": "Context.TRAINING", "prov-ml:source": "custom_metric", "prov-ml:metric_epoch_list": "[0, 0, 0, ..., 4, 4, 4]", "prov-ml:metric_value_list": "[0.000e+00, 1.000e+00, 2.000e+00, ..., 1.872e+03, 1.873e+03, 1.874e+03]", "prov-ml:metric_timestamp_list": "[1749039885844, 1749039885850, 1749039885856, ..., 1749039976155, 1749039976160, 1749039976166]", "prov-ml:artifact_uri": "prov/MetricsType.ZARR_False_zstd_0/artifacts/metrics/Indices_Context.TRAINING_GR0.zarr"}, "Indices2_Context.TRAINING": {"prov-ml:type": "Metric", "prov-ml:name": "Indices2", "prov-ml:context": "Context.TRAINING", "prov-ml:source": "custom_metric", "prov-ml:metric_epoch_list": "[0, 0, 0, ..., 4, 4, 4]", "prov-ml:metric_value_list": "[1000., 1001., 1002., ..., 2872., 2873., 2874.]", "prov-ml:metric_timestamp_list": "[1749039885844, 1749039885850, 1749039885856, ..., 1749039976155, 1749039976160, 1749039976166]", "prov-ml:artifact_uri": "prov/MetricsType.ZARR_False_zstd_0/artifacts/metrics/Indices2_Context.TRAINING_GR0.zarr"}, "Indices3_Context.TRAINING": {"prov-ml:type": "Metric", "prov-ml:name": "Indices3", "prov-ml:context": "Context.TRAINING", "prov-ml:source": "custom_metric", "prov-ml:metric_epoch_list": "[0, 0, 0, ..., 4, 4, 4]", "prov-ml:metric_value_list": "[3000., 3001., 3002., ..., 4872., 4873., 4874.]", "prov-ml:metric_timestamp_list": "[1749039885844, 1749039885850, 1749039885856, ..., 1749039976155, 1749039976160, 1749039976166]", "prov-ml:artifact_uri": "prov/MetricsType.ZARR_False_zstd_0/artifacts/metrics/Indices3_Context.TRAINING_GR0.zarr"}, "Indices4_Context.TRAINING": {"prov-ml:type": "Metric", "prov-ml:name": "Indices4", "prov-ml:context": "Context.TRAINING", "prov-ml:source": "custom_metric", "prov-ml:metric_epoch_list": "[0, 0, 0, ..., 4, 4, 4]", "prov-ml:metric_value_list": "[4000., 4001., 4002., ..., 5872., 5873., 5874.]", "prov-ml:metric_timestamp_list": "[1749039885844, 1749039885850, 1749039885856, ..., 1749039976155, 1749039976160, 1749039976166]", "prov-ml:artifact_uri": "prov/MetricsType.ZARR_False_zstd_0/artifacts/metrics/Indices4_Context.TRAINING_GR0.zarr"}, "Indices5_Context.TRAINING": {"prov-ml:type": "Metric", "prov-ml:name": "Indices5", "prov-ml:context": "Context.TRAINING", "prov-ml:source": "custom_metric", "prov-ml:metric_epoch_list": "[0, 0, 0, ..., 4, 4, 4]", "prov-ml:metric_value_list": "[6000., 6001., 6002., ..., 7872., 7873., 7874.]", "prov-ml:metric_timestamp_list": "[1749039885844, 1749039885850, 1749039885856, ..., 1749039976155, 1749039976160, 1749039976166]", "prov-ml:artifact_uri": "prov/MetricsType.ZARR_False_zstd_0/artifacts/metrics/Indices5_Context.TRAINING_GR0.zarr"}, "MSE_test_Context.EVALUATION": {"prov-ml:type": "Metric", "prov-ml:name": "MSE_test", "prov-ml:context": "Context.EVALUATION", "prov-ml:source": "custom_metric", "prov-ml:metric_epoch_list": "[4, 4, 4, 4, 4, 4, 4, 4, 4, 4, 4, 4, 4, 4, 4, 4, 4, 4, 4, 4, 4, 4, 4, 4, 4, 4, 4, 4, 4, 4, 4, 4, 4, 4, 4, 4, 4, 4, 4, 4, 4, 4, 4, 4, 4, 4, 4, 4, 4, 4, 4, 4, 4, 4, 4, 4, 4, 4, 4, 4, 4, 4, 4, 4, 4, 4, 4, 4, 4, 4, 4, 4, 4, 4, 4, 4, 4, 4, 4, 4, 4, 4, 4, 4, 4, 4, 4, 4, 4, 4, 4, 4, 4, 4, 4, 4, 4, 4, 4, 4, 4, 4, 4, 4, 4, 4, 4, 4, 4, 4, 4, 4, 4, 4, 4, 4, 4, 4, 4, 4, 4, 4, 4, 4, 4, 4, 4, 4, 4, 4, 4, 4, 4, 4, 4, 4, 4, 4, 4, 4, 4, 4, 4, 4, 4, 4, 4, 4, 4, 4, 4, 4, 4, 4, 4, 4, 4, 4, 4, 4, 4, 4, 4, 4, 4, 4, 4, 4, 4, 4, 4, 4, 4, 4, 4, 4, 4, 4, 4, 4, 4, 4, 4, 4, 4, 4, 4, 4, 4, 4, 4, 4, 4, 4, 4, 4, 4, 4, 4, 4, 4, 4, 4, 4, 4, 4, 4, 4, 4, 4, 4, 4, 4, 4, 4, 4, 4, 4, 4, 4, 4, 4, 4, 4, 4, 4, 4, 4, 4, 4, 4, 4, 4, 4, 4, 4, 4, 4, 4, 4, 4, 4, 4, 4, 4, 4, 4, 4, 4, 4, 4, 4, 4, 4, 4, 4, 4, 4, 4, 4, 4, 4, 4, 4, 4, 4, 4, 4, 4, 4, 4, 4, 4, 4, 4, 4, 4, 4, 4, 4, 4, 4, 4, 4, 4, 4, 4, 4, 4, 4, 4, 4, 4, 4, 4, 4, 4, 4, 4, 4, 4, 4, 4, 4, 4, 4, 4, 4, 4, 4, 4, 4, 4]", "prov-ml:metric_value_list": "[0.05574686, 0.06998506, 0.05439059, 0.07532003, 0.06873085, 0.0686828 , 0.06545718, 0.07320954, 0.07331013, 0.07930192, 0.06998589, 0.07345048, 0.07129481, 0.07077616, 0.08516174, 0.06404989, 0.07776228, 0.07813474, 0.08296678, 0.08594216, 0.06743316, 0.07154711, 0.07116461, 0.06481554, 0.06779858, 0.06518622, 0.06270519, 0.08412731, 0.06755915, 0.08383443, 0.0651319 , 0.0718841 , 0.07050937, 0.07414161, 0.07378002, 0.06888928, 0.07171747, 0.07101661, 0.08059821, 0.08085606, 0.07026026, 0.07493051, 0.07201973, 0.06971785, 0.08390608, 0.0753444 , 0.07216357, 0.0742332 , 0.06855609, 0.07656211, 0.07156092, 0.07644335, 0.08059692, 0.07450923, 0.0750808 , 0.06268584, 0.07841621, 0.06059206, 0.07190377, 0.07873356, 0.06593683, 0.07843338, 0.07043107, 0.06688318, 0.06859417, 0.08706812, 0.08254007, 0.06665891, 0.08586781, 0.07207899, 0.06938477, 0.06909167, 0.06528378, 0.07212235, 0.07605806, 0.06676012, 0.0827614 , 0.07732014, 0.07944903, 0.0784362 , 0.07596975, 0.07681351, 0.07381352, 0.06576332, 0.06160937, 0.08240956, 0.07819255, 0.0806741 , 0.06331159, 0.07188498, 0.06973632, 0.08053037, 0.07460757, 0.07170516, 0.06683608, 0.07060742, 0.0635087 , 0.07937893, 0.07776523, 0.0721766 , 0.06152835, 0.07266536, 0.07123831, 0.07480135, 0.08752904, 0.07075148, 0.06686288, 0.06291764, 0.06399357, 0.08534214, 0.08091103, 0.08266463, 0.06636365, 0.07143789, 0.0663696 , 0.07469894, 0.07191171, 0.08492951, 0.07832485, 0.08589303, 0.07631996, 0.07789823, 0.0775726 , 0.08327333, 0.0645368 , 0.06063057, 0.06698181, 0.06385737, 0.08678754, 0.08117124, 0.05781647, 0.07066642, 0.08062478, 0.07002859, 0.08050573, 0.07053641, 0.08489794, 0.079215  , 0.08120406, 0.07226076, 0.08175031, 0.06033505, 0.09157956, 0.0655669 , 0.080437  , 0.06002766, 0.07527452, 0.07240495, 0.07352131, 0.06898109, 0.07592582, 0.07600474, 0.07330869, 0.06391741, 0.06694897, 0.08717117, 0.05947221, 0.04622219, 0.05929955, 0.04856297, 0.05406831, 0.07526832, 0.07572442, 0.06560981, 0.06488077, 0.07042835, 0.04902247, 0.05302164, 0.07962445, 0.05461938, 0.05056523, 0.06085696, 0.06361897, 0.07303008, 0.07369854, 0.07413023, 0.06249052, 0.05918401, 0.07043415, 0.06749513, 0.06903989, 0.06585183, 0.06434568, 0.07223373, 0.0660228 , 0.07391582, 0.07701167, 0.05931395, 0.08133239, 0.07631763, 0.07612377, 0.07867455, 0.08407027, 0.06339393, 0.05618448, 0.0480882 , 0.05150818, 0.05523948, 0.0566165 , 0.0773575 , 0.06292173, 0.04942737, 0.0613002 , 0.05675293, 0.07119176, 0.07672015, 0.0714206 , 0.06367484, 0.06133114, 0.06319567, 0.08036333, 0.06198735, 0.07097656, 0.07705017, 0.05821475, 0.08042523, 0.05851377, 0.0563346 , 0.05743057, 0.0653672 , 0.06281223, 0.06519516, 0.06481171, 0.05001454, 0.06305826, 0.06164199, 0.07989378, 0.06602436, 0.05352983, 0.05766952, 0.06205708, 0.07250633, 0.07220414, 0.07178964, 0.0713444 , 0.06476891, 0.06139499, 0.05818688, 0.06675801, 0.06716439, 0.06524569, 0.07333367, 0.07131212, 0.07111643, 0.07543922, 0.1015355 , 0.07651738, 0.07854273, 0.07593375, 0.06800067, 0.06328883, 0.08089524, 0.07169883, 0.06458024, 0.06466421, 0.06377702, 0.06086897, 0.06267966, 0.07270709, 0.07319834, 0.07392152, 0.06098889, 0.0578389 , 0.06820997, 0.07239747, 0.06748382, 0.07517141, 0.06146179, 0.05406328, 0.05962664, 0.06396515, 0.05565537, 0.05613387, 0.05239382, 0.05258291, 0.05210744, 0.05434668, 0.05006028, 0.04984374, 0.06599098, 0.06009532, 0.07478768, 0.06932106, 0.07941846, 0.07694202, 0.06942776, 0.06642658, 0.06221157, 0.06380095, 0.06274194, 0.0564074 , 0.06395607, 0.05907643, 0.06653007, 0.06458065, 0.05932134, 0.06671828, 0.06444815, 0.05711559, 0.06530114, 0.07075249, 0.06655105, 0.07282533, 0.06390844, 0.07452223, 0.06736753, 0.06221139, 0.07446683, 0.07614037, 0.06461822, 0.06690608, 0.06829625, 0.0666055 ]", "prov-ml:metric_timestamp_list": "[1749039976179, 1749039976184, 1749039976189, 1749039976195, 1749039976200, 1749039976206, 1749039976211, 1749039976216, 1749039976221, 1749039976227, 1749039976232, 1749039976237, 1749039976243, 1749039976248, 1749039976254, 1749039976259, 1749039976265, 1749039976270, 1749039976275, 1749039976281, 1749039976286, 1749039976291, 1749039976378, 1749039976384, 1749039976389, 1749039976394, 1749039976399, 1749039976405, 1749039976410, 1749039976415, 1749039976420, 1749039976426, 1749039976431, 1749039976436, 1749039976442, 1749039976447, 1749039976453, 1749039976458, 1749039976463, 1749039976469, 1749039976474, 1749039976479, 1749039976484, 1749039976490, 1749039976495, 1749039976500, 1749039976505, 1749039976511, 1749039976517, 1749039976522, 1749039976527, 1749039976533, 1749039976538, 1749039976543, 1749039976549, 1749039976554, 1749039976559, 1749039976564, 1749039976570, 1749039976575, 1749039976581, 1749039976586, 1749039976591, 1749039976596, 1749039976602, 1749039976607, 1749039976612, 1749039976617, 1749039976623, 1749039976628, 1749039976633, 1749039976639, 1749039976644, 1749039976649, 1749039976654, 1749039976660, 1749039976665, 1749039976670, 1749039976676, 1749039976681, 1749039976686, 1749039976691, 1749039976697, 1749039976702, 1749039976708, 1749039976713, 1749039976718, 1749039976724, 1749039976729, 1749039976734, 1749039976739, 1749039976745, 1749039976751, 1749039976756, 1749039976761, 1749039976767, 1749039976772, 1749039976778, 1749039976783, 1749039976788, 1749039976794, 1749039976799, 1749039976804, 1749039976810, 1749039976815, 1749039976820, 1749039976826, 1749039976831, 1749039976836, 1749039976842, 1749039976847, 1749039976852, 1749039976857, 1749039976863, 1749039976868, 1749039976873, 1749039976879, 1749039976884, 1749039976889, 1749039976894, 1749039976900, 1749039976905, 1749039976937, 1749039976942, 1749039976948, 1749039976953, 1749039976959, 1749039976964, 1749039976969, 1749039976975, 1749039976980, 1749039976985, 1749039976991, 1749039976996, 1749039977001, 1749039977007, 1749039977012, 1749039977017, 1749039977023, 1749039977029, 1749039977034, 1749039977039, 1749039977045, 1749039977050, 1749039977055, 1749039977061, 1749039977066, 1749039977071, 1749039977077, 1749039977082, 1749039977088, 1749039977093, 1749039977098, 1749039977103, 1749039977109, 1749039977114, 1749039977119, 1749039977125, 1749039977130, 1749039977135, 1749039977140, 1749039977146, 1749039977151, 1749039977156, 1749039977162, 1749039977167, 1749039977172, 1749039977178, 1749039977183, 1749039977188, 1749039977194, 1749039977199, 1749039977204, 1749039977210, 1749039977215, 1749039977221, 1749039977226, 1749039977231, 1749039977237, 1749039977242, 1749039977247, 1749039977253, 1749039977258, 1749039977264, 1749039977269, 1749039977275, 1749039977280, 1749039977285, 1749039977291, 1749039977296, 1749039977301, 1749039977307, 1749039977312, 1749039977317, 1749039977322, 1749039977328, 1749039977333, 1749039977338, 1749039977344, 1749039977349, 1749039977354, 1749039977360, 1749039977365, 1749039977370, 1749039977375, 1749039977381, 1749039977386, 1749039977391, 1749039977397, 1749039977402, 1749039977407, 1749039977413, 1749039977418, 1749039977423, 1749039977428, 1749039977434, 1749039977439, 1749039977444, 1749039977450, 1749039977455, 1749039977461, 1749039977466, 1749039977517, 1749039977523, 1749039977528, 1749039977534, 1749039977539, 1749039977545, 1749039977550, 1749039977555, 1749039977561, 1749039977566, 1749039977571, 1749039977577, 1749039977582, 1749039977588, 1749039977593, 1749039977598, 1749039977603, 1749039977609, 1749039977614, 1749039977619, 1749039977625, 1749039977630, 1749039977635, 1749039977640, 1749039977646, 1749039977651, 1749039977656, 1749039977661, 1749039977667, 1749039977672, 1749039977677, 1749039977683, 1749039977688, 1749039977693, 1749039977698, 1749039977704, 1749039977709, 1749039977715, 1749039977720, 1749039977725, 1749039977731, 1749039977736, 1749039977742, 1749039977747, 1749039977752, 1749039977758, 1749039977763, 1749039977769, 1749039977774, 1749039977780, 1749039977785, 1749039977790, 1749039977796, 1749039977801, 1749039977806, 1749039977811, 1749039977817, 1749039977822, 1749039977828, 1749039977833, 1749039977838, 1749039977844, 1749039977849, 1749039977854, 1749039977859, 1749039977865, 1749039977870, 1749039977875, 1749039977881, 1749039977886, 1749039977891, 1749039977897, 1749039977902, 1749039977907, 1749039977913, 1749039977918, 1749039977923, 1749039977929, 1749039977934, 1749039977939, 1749039977945, 1749039977951, 1749039977956, 1749039977962, 1749039977967, 1749039977972, 1749039977978, 1749039977983, 1749039977988, 1749039977993, 1749039977996]", "prov-ml:artifact_uri": "prov/MetricsType.ZARR_False_zstd_0/artifacts/metrics/MSE_test_Context.EVALUATION_GR0.zarr"}, "execution_start_time": {"prov-ml:parameter_value": "1749039885.7781012", "prov-ml:type": "Parameter"}, "model_name": {"prov-ml:parameter_value": "mnist_model_final", "prov-ml:type": "Parameter"}, "total_params": {"prov-ml:parameter_value": "7850", "prov-ml:type": "Parameter"}, "memory_of_model": {"prov-ml:parameter_value": "0.0314", "prov-ml:type": "Parameter"}, "total_memory_load_of_model": {"prov-ml:parameter_value": "0.09419999999999999", "prov-ml:type": "Parameter"}, "execution_end_time": {"prov-ml:parameter_value": "1749039978.0059147", "prov-ml:type": "Parameter"}, "final_run_statistics": {"prov-ml:type": "RunStatistics"}, "datasets": {}, "train_dataset": {"prov-ml:type": "Dataset", "prov-ml:size": "32", "prov-ml:workers": "0", "prov-ml:steps": "313", "prov-ml:samples": "10000"}, "prov/MetricsType.ZARR_False_zstd_0/artifacts/mnist_model_final/mnist_model_final_0.pth": [{"prov-ml:type": "ModelVersion", "prov-ml:creation_epoch": "None", "prov-ml:artifact_uri": "prov/MetricsType.ZARR_False_zstd_0/artifacts/mnist_model_final/mnist_model_final_0.pth", "prov-ml:creation_timestamp": "2025-06-04 14:26:18.006000", "prov-ml:last_modified_timestamp": "2025-06-04 14:26:18.006000"}, {"prov-ml:artifact_path": "prov/MetricsType.ZARR_False_zstd_0/artifacts/mnist_model_final/mnist_model_final_0.pth"}], "prov/MetricsType.ZARR_False_blosc_lz4_0/artifacts/mnist_model_version_0/mnist_model_version_0_0.pth": {"prov-ml:artifact_path": "prov/MetricsType.ZARR_False_blosc_lz4_0/artifacts/mnist_model_version_0/mnist_model_version_0_0.pth"}, "prov/MetricsType.ZARR_False_blosc_lz4_0/artifacts/mnist_model_version_1/mnist_model_version_1_0.pth": {"prov-ml:artifact_path": "prov/MetricsType.ZARR_False_blosc_lz4_0/artifacts/mnist_model_version_1/mnist_model_version_1_0.pth"}, "prov/MetricsType.ZARR_False_blosc_lz4_0/artifacts/mnist_model_version_2/mnist_model_version_2_0.pth": {"prov-ml:artifact_path": "prov/MetricsType.ZARR_False_blosc_lz4_0/artifacts/mnist_model_version_2/mnist_model_version_2_0.pth"}, "prov/MetricsType.ZARR_False_blosc_lz4_0/artifacts/mnist_model_version_3/mnist_model_version_3_0.pth": {"prov-ml:artifact_path": "prov/MetricsType.ZARR_False_blosc_lz4_0/artifacts/mnist_model_version_3/mnist_model_version_3_0.pth"}, "prov/MetricsType.ZARR_False_blosc_lz4_0/artifacts/mnist_model_version_4/mnist_model_version_4_0.pth": {"prov-ml:artifact_path": "prov/MetricsType.ZARR_False_blosc_lz4_0/artifacts/mnist_model_version_4/mnist_model_version_4_0.pth"}, "prov/MetricsType.ZARR_False_blosc_lz4_0/artifacts/mnist_model_final/mnist_model_final_0.pth": {"prov-ml:artifact_path": "prov/MetricsType.ZARR_False_blosc_lz4_0/artifacts/mnist_model_final/mnist_model_final_0.pth"}, "prov/MetricsType.ZARR_False_blosc_lz4_0/artifacts/metrics/MSE_train_Context.TRAINING_GR0.zarr": {"prov-ml:artifact_path": "prov/MetricsType.ZARR_False_blosc_lz4_0/artifacts/metrics/MSE_train_Context.TRAINING_GR0.zarr"}, "prov/MetricsType.ZARR_False_blosc_lz4_0/artifacts/metrics/MSE_train2_Context.TRAINING_GR0.zarr": {"prov-ml:artifact_path": "prov/MetricsType.ZARR_False_blosc_lz4_0/artifacts/metrics/MSE_train2_Context.TRAINING_GR0.zarr"}, "prov/MetricsType.ZARR_False_blosc_lz4_0/artifacts/metrics/MSE_train3_Context.TRAINING_GR0.zarr": {"prov-ml:artifact_path": "prov/MetricsType.ZARR_False_blosc_lz4_0/artifacts/metrics/MSE_train3_Context.TRAINING_GR0.zarr"}, "prov/MetricsType.ZARR_False_blosc_lz4_0/artifacts/metrics/MSE_train4_Context.TRAINING_GR0.zarr": {"prov-ml:artifact_path": "prov/MetricsType.ZARR_False_blosc_lz4_0/artifacts/metrics/MSE_train4_Context.TRAINING_GR0.zarr"}, "prov/MetricsType.ZARR_False_blosc_lz4_0/artifacts/metrics/MSE_train5_Context.TRAINING_GR0.zarr": {"prov-ml:artifact_path": "prov/MetricsType.ZARR_False_blosc_lz4_0/artifacts/metrics/MSE_train5_Context.TRAINING_GR0.zarr"}, "prov/MetricsType.ZARR_False_blosc_lz4_0/artifacts/metrics/Indices_Context.TRAINING_GR0.zarr": {"prov-ml:artifact_path": "prov/MetricsType.ZARR_False_blosc_lz4_0/artifacts/metrics/Indices_Context.TRAINING_GR0.zarr"}, "prov/MetricsType.ZARR_False_blosc_lz4_0/artifacts/metrics/Indices2_Context.TRAINING_GR0.zarr": {"prov-ml:artifact_path": "prov/MetricsType.ZARR_False_blosc_lz4_0/artifacts/metrics/Indices2_Context.TRAINING_GR0.zarr"}, "prov/MetricsType.ZARR_False_blosc_lz4_0/artifacts/metrics/Indices3_Context.TRAINING_GR0.zarr": {"prov-ml:artifact_path": "prov/MetricsType.ZARR_False_blosc_lz4_0/artifacts/metrics/Indices3_Context.TRAINING_GR0.zarr"}, "prov/MetricsType.ZARR_False_blosc_lz4_0/artifacts/metrics/Indices4_Context.TRAINING_GR0.zarr": {"prov-ml:artifact_path": "prov/MetricsType.ZARR_False_blosc_lz4_0/artifacts/metrics/Indices4_Context.TRAINING_GR0.zarr"}, "prov/MetricsType.ZARR_False_blosc_lz4_0/artifacts/metrics/Indices5_Context.TRAINING_GR0.zarr": {"prov-ml:artifact_path": "prov/MetricsType.ZARR_False_blosc_lz4_0/artifacts/metrics/Indices5_Context.TRAINING_GR0.zarr"}, "prov/MetricsType.ZARR_False_blosc_lz4_0/artifacts/metrics/MSE_test_Context.EVALUATION_GR0.zarr": {"prov-ml:artifact_path": "prov/MetricsType.ZARR_False_blosc_lz4_0/artifacts/metrics/MSE_test_Context.EVALUATION_GR0.zarr"}, "prov/MetricsType.ZARR_False_blosc_lz4hc_0/artifacts/mnist_model_version_0/mnist_model_version_0_0.pth": {"prov-ml:artifact_path": "prov/MetricsType.ZARR_False_blosc_lz4hc_0/artifacts/mnist_model_version_0/mnist_model_version_0_0.pth"}, "prov/MetricsType.ZARR_False_blosc_lz4hc_0/artifacts/mnist_model_version_1/mnist_model_version_1_0.pth": {"prov-ml:artifact_path": "prov/MetricsType.ZARR_False_blosc_lz4hc_0/artifacts/mnist_model_version_1/mnist_model_version_1_0.pth"}, "prov/MetricsType.ZARR_False_blosc_lz4hc_0/artifacts/mnist_model_version_2/mnist_model_version_2_0.pth": {"prov-ml:artifact_path": "prov/MetricsType.ZARR_False_blosc_lz4hc_0/artifacts/mnist_model_version_2/mnist_model_version_2_0.pth"}, "prov/MetricsType.ZARR_False_blosc_lz4hc_0/artifacts/mnist_model_version_3/mnist_model_version_3_0.pth": {"prov-ml:artifact_path": "prov/MetricsType.ZARR_False_blosc_lz4hc_0/artifacts/mnist_model_version_3/mnist_model_version_3_0.pth"}, "prov/MetricsType.ZARR_False_blosc_lz4hc_0/artifacts/mnist_model_version_4/mnist_model_version_4_0.pth": {"prov-ml:artifact_path": "prov/MetricsType.ZARR_False_blosc_lz4hc_0/artifacts/mnist_model_version_4/mnist_model_version_4_0.pth"}, "prov/MetricsType.ZARR_False_blosc_lz4hc_0/artifacts/mnist_model_final/mnist_model_final_0.pth": {"prov-ml:artifact_path": "prov/MetricsType.ZARR_False_blosc_lz4hc_0/artifacts/mnist_model_final/mnist_model_final_0.pth"}, "prov/MetricsType.ZARR_False_blosc_lz4hc_0/artifacts/metrics/MSE_train_Context.TRAINING_GR0.zarr": {"prov-ml:artifact_path": "prov/MetricsType.ZARR_False_blosc_lz4hc_0/artifacts/metrics/MSE_train_Context.TRAINING_GR0.zarr"}, "prov/MetricsType.ZARR_False_blosc_lz4hc_0/artifacts/metrics/MSE_train2_Context.TRAINING_GR0.zarr": {"prov-ml:artifact_path": "prov/MetricsType.ZARR_False_blosc_lz4hc_0/artifacts/metrics/MSE_train2_Context.TRAINING_GR0.zarr"}, "prov/MetricsType.ZARR_False_blosc_lz4hc_0/artifacts/metrics/MSE_train3_Context.TRAINING_GR0.zarr": {"prov-ml:artifact_path": "prov/MetricsType.ZARR_False_blosc_lz4hc_0/artifacts/metrics/MSE_train3_Context.TRAINING_GR0.zarr"}, "prov/MetricsType.ZARR_False_blosc_lz4hc_0/artifacts/metrics/MSE_train4_Context.TRAINING_GR0.zarr": {"prov-ml:artifact_path": "prov/MetricsType.ZARR_False_blosc_lz4hc_0/artifacts/metrics/MSE_train4_Context.TRAINING_GR0.zarr"}, "prov/MetricsType.ZARR_False_blosc_lz4hc_0/artifacts/metrics/MSE_train5_Context.TRAINING_GR0.zarr": {"prov-ml:artifact_path": "prov/MetricsType.ZARR_False_blosc_lz4hc_0/artifacts/metrics/MSE_train5_Context.TRAINING_GR0.zarr"}, "prov/MetricsType.ZARR_False_blosc_lz4hc_0/artifacts/metrics/Indices_Context.TRAINING_GR0.zarr": {"prov-ml:artifact_path": "prov/MetricsType.ZARR_False_blosc_lz4hc_0/artifacts/metrics/Indices_Context.TRAINING_GR0.zarr"}, "prov/MetricsType.ZARR_False_blosc_lz4hc_0/artifacts/metrics/Indices2_Context.TRAINING_GR0.zarr": {"prov-ml:artifact_path": "prov/MetricsType.ZARR_False_blosc_lz4hc_0/artifacts/metrics/Indices2_Context.TRAINING_GR0.zarr"}, "prov/MetricsType.ZARR_False_blosc_lz4hc_0/artifacts/metrics/Indices3_Context.TRAINING_GR0.zarr": {"prov-ml:artifact_path": "prov/MetricsType.ZARR_False_blosc_lz4hc_0/artifacts/metrics/Indices3_Context.TRAINING_GR0.zarr"}, "prov/MetricsType.ZARR_False_blosc_lz4hc_0/artifacts/metrics/Indices4_Context.TRAINING_GR0.zarr": {"prov-ml:artifact_path": "prov/MetricsType.ZARR_False_blosc_lz4hc_0/artifacts/metrics/Indices4_Context.TRAINING_GR0.zarr"}, "prov/MetricsType.ZARR_False_blosc_lz4hc_0/artifacts/metrics/Indices5_Context.TRAINING_GR0.zarr": {"prov-ml:artifact_path": "prov/MetricsType.ZARR_False_blosc_lz4hc_0/artifacts/metrics/Indices5_Context.TRAINING_GR0.zarr"}, "prov/MetricsType.ZARR_False_blosc_lz4hc_0/artifacts/metrics/MSE_test_Context.EVALUATION_GR0.zarr": {"prov-ml:artifact_path": "prov/MetricsType.ZARR_False_blosc_lz4hc_0/artifacts/metrics/MSE_test_Context.EVALUATION_GR0.zarr"}, "prov/MetricsType.ZARR_False_blosc_blosclz_0/artifacts/mnist_model_version_0/mnist_model_version_0_0.pth": {"prov-ml:artifact_path": "prov/MetricsType.ZARR_False_blosc_blosclz_0/artifacts/mnist_model_version_0/mnist_model_version_0_0.pth"}, "prov/MetricsType.ZARR_False_blosc_blosclz_0/artifacts/mnist_model_version_1/mnist_model_version_1_0.pth": {"prov-ml:artifact_path": "prov/MetricsType.ZARR_False_blosc_blosclz_0/artifacts/mnist_model_version_1/mnist_model_version_1_0.pth"}, "prov/MetricsType.ZARR_False_blosc_blosclz_0/artifacts/mnist_model_version_2/mnist_model_version_2_0.pth": {"prov-ml:artifact_path": "prov/MetricsType.ZARR_False_blosc_blosclz_0/artifacts/mnist_model_version_2/mnist_model_version_2_0.pth"}, "prov/MetricsType.ZARR_False_blosc_blosclz_0/artifacts/mnist_model_version_3/mnist_model_version_3_0.pth": {"prov-ml:artifact_path": "prov/MetricsType.ZARR_False_blosc_blosclz_0/artifacts/mnist_model_version_3/mnist_model_version_3_0.pth"}, "prov/MetricsType.ZARR_False_blosc_blosclz_0/artifacts/mnist_model_version_4/mnist_model_version_4_0.pth": {"prov-ml:artifact_path": "prov/MetricsType.ZARR_False_blosc_blosclz_0/artifacts/mnist_model_version_4/mnist_model_version_4_0.pth"}, "prov/MetricsType.ZARR_False_blosc_blosclz_0/artifacts/mnist_model_final/mnist_model_final_0.pth": {"prov-ml:artifact_path": "prov/MetricsType.ZARR_False_blosc_blosclz_0/artifacts/mnist_model_final/mnist_model_final_0.pth"}, "prov/MetricsType.ZARR_False_blosc_blosclz_0/artifacts/metrics/MSE_train_Context.TRAINING_GR0.zarr": {"prov-ml:artifact_path": "prov/MetricsType.ZARR_False_blosc_blosclz_0/artifacts/metrics/MSE_train_Context.TRAINING_GR0.zarr"}, "prov/MetricsType.ZARR_False_blosc_blosclz_0/artifacts/metrics/MSE_train2_Context.TRAINING_GR0.zarr": {"prov-ml:artifact_path": "prov/MetricsType.ZARR_False_blosc_blosclz_0/artifacts/metrics/MSE_train2_Context.TRAINING_GR0.zarr"}, "prov/MetricsType.ZARR_False_blosc_blosclz_0/artifacts/metrics/MSE_train3_Context.TRAINING_GR0.zarr": {"prov-ml:artifact_path": "prov/MetricsType.ZARR_False_blosc_blosclz_0/artifacts/metrics/MSE_train3_Context.TRAINING_GR0.zarr"}, "prov/MetricsType.ZARR_False_blosc_blosclz_0/artifacts/metrics/MSE_train4_Context.TRAINING_GR0.zarr": {"prov-ml:artifact_path": "prov/MetricsType.ZARR_False_blosc_blosclz_0/artifacts/metrics/MSE_train4_Context.TRAINING_GR0.zarr"}, "prov/MetricsType.ZARR_False_blosc_blosclz_0/artifacts/metrics/MSE_train5_Context.TRAINING_GR0.zarr": {"prov-ml:artifact_path": "prov/MetricsType.ZARR_False_blosc_blosclz_0/artifacts/metrics/MSE_train5_Context.TRAINING_GR0.zarr"}, "prov/MetricsType.ZARR_False_blosc_blosclz_0/artifacts/metrics/Indices_Context.TRAINING_GR0.zarr": {"prov-ml:artifact_path": "prov/MetricsType.ZARR_False_blosc_blosclz_0/artifacts/metrics/Indices_Context.TRAINING_GR0.zarr"}, "prov/MetricsType.ZARR_False_blosc_blosclz_0/artifacts/metrics/Indices2_Context.TRAINING_GR0.zarr": {"prov-ml:artifact_path": "prov/MetricsType.ZARR_False_blosc_blosclz_0/artifacts/metrics/Indices2_Context.TRAINING_GR0.zarr"}, "prov/MetricsType.ZARR_False_blosc_blosclz_0/artifacts/metrics/Indices3_Context.TRAINING_GR0.zarr": {"prov-ml:artifact_path": "prov/MetricsType.ZARR_False_blosc_blosclz_0/artifacts/metrics/Indices3_Context.TRAINING_GR0.zarr"}, "prov/MetricsType.ZARR_False_blosc_blosclz_0/artifacts/metrics/Indices4_Context.TRAINING_GR0.zarr": {"prov-ml:artifact_path": "prov/MetricsType.ZARR_False_blosc_blosclz_0/artifacts/metrics/Indices4_Context.TRAINING_GR0.zarr"}, "prov/MetricsType.ZARR_False_blosc_blosclz_0/artifacts/metrics/Indices5_Context.TRAINING_GR0.zarr": {"prov-ml:artifact_path": "prov/MetricsType.ZARR_False_blosc_blosclz_0/artifacts/metrics/Indices5_Context.TRAINING_GR0.zarr"}, "prov/MetricsType.ZARR_False_blosc_blosclz_0/artifacts/metrics/MSE_test_Context.EVALUATION_GR0.zarr": {"prov-ml:artifact_path": "prov/MetricsType.ZARR_False_blosc_blosclz_0/artifacts/metrics/MSE_test_Context.EVALUATION_GR0.zarr"}, "prov/MetricsType.ZARR_False_blosc_zstd_0/artifacts/mnist_model_version_0/mnist_model_version_0_0.pth": {"prov-ml:artifact_path": "prov/MetricsType.ZARR_False_blosc_zstd_0/artifacts/mnist_model_version_0/mnist_model_version_0_0.pth"}, "prov/MetricsType.ZARR_False_blosc_zstd_0/artifacts/mnist_model_version_1/mnist_model_version_1_0.pth": {"prov-ml:artifact_path": "prov/MetricsType.ZARR_False_blosc_zstd_0/artifacts/mnist_model_version_1/mnist_model_version_1_0.pth"}, "prov/MetricsType.ZARR_False_blosc_zstd_0/artifacts/mnist_model_version_2/mnist_model_version_2_0.pth": {"prov-ml:artifact_path": "prov/MetricsType.ZARR_False_blosc_zstd_0/artifacts/mnist_model_version_2/mnist_model_version_2_0.pth"}, "prov/MetricsType.ZARR_False_blosc_zstd_0/artifacts/mnist_model_version_3/mnist_model_version_3_0.pth": {"prov-ml:artifact_path": "prov/MetricsType.ZARR_False_blosc_zstd_0/artifacts/mnist_model_version_3/mnist_model_version_3_0.pth"}, "prov/MetricsType.ZARR_False_blosc_zstd_0/artifacts/mnist_model_version_4/mnist_model_version_4_0.pth": {"prov-ml:artifact_path": "prov/MetricsType.ZARR_False_blosc_zstd_0/artifacts/mnist_model_version_4/mnist_model_version_4_0.pth"}, "prov/MetricsType.ZARR_False_blosc_zstd_0/artifacts/mnist_model_final/mnist_model_final_0.pth": {"prov-ml:artifact_path": "prov/MetricsType.ZARR_False_blosc_zstd_0/artifacts/mnist_model_final/mnist_model_final_0.pth"}, "prov/MetricsType.ZARR_False_blosc_zstd_0/artifacts/metrics/MSE_train_Context.TRAINING_GR0.zarr": {"prov-ml:artifact_path": "prov/MetricsType.ZARR_False_blosc_zstd_0/artifacts/metrics/MSE_train_Context.TRAINING_GR0.zarr"}, "prov/MetricsType.ZARR_False_blosc_zstd_0/artifacts/metrics/MSE_train2_Context.TRAINING_GR0.zarr": {"prov-ml:artifact_path": "prov/MetricsType.ZARR_False_blosc_zstd_0/artifacts/metrics/MSE_train2_Context.TRAINING_GR0.zarr"}, "prov/MetricsType.ZARR_False_blosc_zstd_0/artifacts/metrics/MSE_train3_Context.TRAINING_GR0.zarr": {"prov-ml:artifact_path": "prov/MetricsType.ZARR_False_blosc_zstd_0/artifacts/metrics/MSE_train3_Context.TRAINING_GR0.zarr"}, "prov/MetricsType.ZARR_False_blosc_zstd_0/artifacts/metrics/MSE_train4_Context.TRAINING_GR0.zarr": {"prov-ml:artifact_path": "prov/MetricsType.ZARR_False_blosc_zstd_0/artifacts/metrics/MSE_train4_Context.TRAINING_GR0.zarr"}, "prov/MetricsType.ZARR_False_blosc_zstd_0/artifacts/metrics/MSE_train5_Context.TRAINING_GR0.zarr": {"prov-ml:artifact_path": "prov/MetricsType.ZARR_False_blosc_zstd_0/artifacts/metrics/MSE_train5_Context.TRAINING_GR0.zarr"}, "prov/MetricsType.ZARR_False_blosc_zstd_0/artifacts/metrics/Indices_Context.TRAINING_GR0.zarr": {"prov-ml:artifact_path": "prov/MetricsType.ZARR_False_blosc_zstd_0/artifacts/metrics/Indices_Context.TRAINING_GR0.zarr"}, "prov/MetricsType.ZARR_False_blosc_zstd_0/artifacts/metrics/Indices2_Context.TRAINING_GR0.zarr": {"prov-ml:artifact_path": "prov/MetricsType.ZARR_False_blosc_zstd_0/artifacts/metrics/Indices2_Context.TRAINING_GR0.zarr"}, "prov/MetricsType.ZARR_False_blosc_zstd_0/artifacts/metrics/Indices3_Context.TRAINING_GR0.zarr": {"prov-ml:artifact_path": "prov/MetricsType.ZARR_False_blosc_zstd_0/artifacts/metrics/Indices3_Context.TRAINING_GR0.zarr"}, "prov/MetricsType.ZARR_False_blosc_zstd_0/artifacts/metrics/Indices4_Context.TRAINING_GR0.zarr": {"prov-ml:artifact_path": "prov/MetricsType.ZARR_False_blosc_zstd_0/artifacts/metrics/Indices4_Context.TRAINING_GR0.zarr"}, "prov/MetricsType.ZARR_False_blosc_zstd_0/artifacts/metrics/Indices5_Context.TRAINING_GR0.zarr": {"prov-ml:artifact_path": "prov/MetricsType.ZARR_False_blosc_zstd_0/artifacts/metrics/Indices5_Context.TRAINING_GR0.zarr"}, "prov/MetricsType.ZARR_False_blosc_zstd_0/artifacts/metrics/MSE_test_Context.EVALUATION_GR0.zarr": {"prov-ml:artifact_path": "prov/MetricsType.ZARR_False_blosc_zstd_0/artifacts/metrics/MSE_test_Context.EVALUATION_GR0.zarr"}, "prov/MetricsType.ZARR_False_blosc_zlib_0/artifacts/mnist_model_version_0/mnist_model_version_0_0.pth": {"prov-ml:artifact_path": "prov/MetricsType.ZARR_False_blosc_zlib_0/artifacts/mnist_model_version_0/mnist_model_version_0_0.pth"}, "prov/MetricsType.ZARR_False_blosc_zlib_0/artifacts/mnist_model_version_1/mnist_model_version_1_0.pth": {"prov-ml:artifact_path": "prov/MetricsType.ZARR_False_blosc_zlib_0/artifacts/mnist_model_version_1/mnist_model_version_1_0.pth"}, "prov/MetricsType.ZARR_False_blosc_zlib_0/artifacts/mnist_model_version_2/mnist_model_version_2_0.pth": {"prov-ml:artifact_path": "prov/MetricsType.ZARR_False_blosc_zlib_0/artifacts/mnist_model_version_2/mnist_model_version_2_0.pth"}, "prov/MetricsType.ZARR_False_blosc_zlib_0/artifacts/mnist_model_version_3/mnist_model_version_3_0.pth": {"prov-ml:artifact_path": "prov/MetricsType.ZARR_False_blosc_zlib_0/artifacts/mnist_model_version_3/mnist_model_version_3_0.pth"}, "prov/MetricsType.ZARR_False_blosc_zlib_0/artifacts/mnist_model_version_4/mnist_model_version_4_0.pth": {"prov-ml:artifact_path": "prov/MetricsType.ZARR_False_blosc_zlib_0/artifacts/mnist_model_version_4/mnist_model_version_4_0.pth"}, "prov/MetricsType.ZARR_False_blosc_zlib_0/artifacts/mnist_model_final/mnist_model_final_0.pth": {"prov-ml:artifact_path": "prov/MetricsType.ZARR_False_blosc_zlib_0/artifacts/mnist_model_final/mnist_model_final_0.pth"}, "prov/MetricsType.ZARR_False_blosc_zlib_0/artifacts/metrics/MSE_train_Context.TRAINING_GR0.zarr": {"prov-ml:artifact_path": "prov/MetricsType.ZARR_False_blosc_zlib_0/artifacts/metrics/MSE_train_Context.TRAINING_GR0.zarr"}, "prov/MetricsType.ZARR_False_blosc_zlib_0/artifacts/metrics/MSE_train2_Context.TRAINING_GR0.zarr": {"prov-ml:artifact_path": "prov/MetricsType.ZARR_False_blosc_zlib_0/artifacts/metrics/MSE_train2_Context.TRAINING_GR0.zarr"}, "prov/MetricsType.ZARR_False_blosc_zlib_0/artifacts/metrics/MSE_train3_Context.TRAINING_GR0.zarr": {"prov-ml:artifact_path": "prov/MetricsType.ZARR_False_blosc_zlib_0/artifacts/metrics/MSE_train3_Context.TRAINING_GR0.zarr"}, "prov/MetricsType.ZARR_False_blosc_zlib_0/artifacts/metrics/MSE_train4_Context.TRAINING_GR0.zarr": {"prov-ml:artifact_path": "prov/MetricsType.ZARR_False_blosc_zlib_0/artifacts/metrics/MSE_train4_Context.TRAINING_GR0.zarr"}, "prov/MetricsType.ZARR_False_blosc_zlib_0/artifacts/metrics/MSE_train5_Context.TRAINING_GR0.zarr": {"prov-ml:artifact_path": "prov/MetricsType.ZARR_False_blosc_zlib_0/artifacts/metrics/MSE_train5_Context.TRAINING_GR0.zarr"}, "prov/MetricsType.ZARR_False_blosc_zlib_0/artifacts/metrics/Indices_Context.TRAINING_GR0.zarr": {"prov-ml:artifact_path": "prov/MetricsType.ZARR_False_blosc_zlib_0/artifacts/metrics/Indices_Context.TRAINING_GR0.zarr"}, "prov/MetricsType.ZARR_False_blosc_zlib_0/artifacts/metrics/Indices2_Context.TRAINING_GR0.zarr": {"prov-ml:artifact_path": "prov/MetricsType.ZARR_False_blosc_zlib_0/artifacts/metrics/Indices2_Context.TRAINING_GR0.zarr"}, "prov/MetricsType.ZARR_False_blosc_zlib_0/artifacts/metrics/Indices3_Context.TRAINING_GR0.zarr": {"prov-ml:artifact_path": "prov/MetricsType.ZARR_False_blosc_zlib_0/artifacts/metrics/Indices3_Context.TRAINING_GR0.zarr"}, "prov/MetricsType.ZARR_False_blosc_zlib_0/artifacts/metrics/Indices4_Context.TRAINING_GR0.zarr": {"prov-ml:artifact_path": "prov/MetricsType.ZARR_False_blosc_zlib_0/artifacts/metrics/Indices4_Context.TRAINING_GR0.zarr"}, "prov/MetricsType.ZARR_False_blosc_zlib_0/artifacts/metrics/Indices5_Context.TRAINING_GR0.zarr": {"prov-ml:artifact_path": "prov/MetricsType.ZARR_False_blosc_zlib_0/artifacts/metrics/Indices5_Context.TRAINING_GR0.zarr"}, "prov/MetricsType.ZARR_False_blosc_zlib_0/artifacts/metrics/MSE_test_Context.EVALUATION_GR0.zarr": {"prov-ml:artifact_path": "prov/MetricsType.ZARR_False_blosc_zlib_0/artifacts/metrics/MSE_test_Context.EVALUATION_GR0.zarr"}, "prov/MetricsType.ZARR_False_gzip_0/artifacts/mnist_model_version_0/mnist_model_version_0_0.pth": {"prov-ml:artifact_path": "prov/MetricsType.ZARR_False_gzip_0/artifacts/mnist_model_version_0/mnist_model_version_0_0.pth"}, "prov/MetricsType.ZARR_False_gzip_0/artifacts/mnist_model_version_1/mnist_model_version_1_0.pth": {"prov-ml:artifact_path": "prov/MetricsType.ZARR_False_gzip_0/artifacts/mnist_model_version_1/mnist_model_version_1_0.pth"}, "prov/MetricsType.ZARR_False_gzip_0/artifacts/mnist_model_version_2/mnist_model_version_2_0.pth": {"prov-ml:artifact_path": "prov/MetricsType.ZARR_False_gzip_0/artifacts/mnist_model_version_2/mnist_model_version_2_0.pth"}, "prov/MetricsType.ZARR_False_gzip_0/artifacts/mnist_model_version_3/mnist_model_version_3_0.pth": {"prov-ml:artifact_path": "prov/MetricsType.ZARR_False_gzip_0/artifacts/mnist_model_version_3/mnist_model_version_3_0.pth"}, "prov/MetricsType.ZARR_False_gzip_0/artifacts/mnist_model_version_4/mnist_model_version_4_0.pth": {"prov-ml:artifact_path": "prov/MetricsType.ZARR_False_gzip_0/artifacts/mnist_model_version_4/mnist_model_version_4_0.pth"}, "prov/MetricsType.ZARR_False_gzip_0/artifacts/mnist_model_final/mnist_model_final_0.pth": {"prov-ml:artifact_path": "prov/MetricsType.ZARR_False_gzip_0/artifacts/mnist_model_final/mnist_model_final_0.pth"}, "prov/MetricsType.ZARR_False_gzip_0/artifacts/metrics/MSE_train_Context.TRAINING_GR0.zarr": {"prov-ml:artifact_path": "prov/MetricsType.ZARR_False_gzip_0/artifacts/metrics/MSE_train_Context.TRAINING_GR0.zarr"}, "prov/MetricsType.ZARR_False_gzip_0/artifacts/metrics/MSE_train2_Context.TRAINING_GR0.zarr": {"prov-ml:artifact_path": "prov/MetricsType.ZARR_False_gzip_0/artifacts/metrics/MSE_train2_Context.TRAINING_GR0.zarr"}, "prov/MetricsType.ZARR_False_gzip_0/artifacts/metrics/MSE_train3_Context.TRAINING_GR0.zarr": {"prov-ml:artifact_path": "prov/MetricsType.ZARR_False_gzip_0/artifacts/metrics/MSE_train3_Context.TRAINING_GR0.zarr"}, "prov/MetricsType.ZARR_False_gzip_0/artifacts/metrics/MSE_train4_Context.TRAINING_GR0.zarr": {"prov-ml:artifact_path": "prov/MetricsType.ZARR_False_gzip_0/artifacts/metrics/MSE_train4_Context.TRAINING_GR0.zarr"}, "prov/MetricsType.ZARR_False_gzip_0/artifacts/metrics/MSE_train5_Context.TRAINING_GR0.zarr": {"prov-ml:artifact_path": "prov/MetricsType.ZARR_False_gzip_0/artifacts/metrics/MSE_train5_Context.TRAINING_GR0.zarr"}, "prov/MetricsType.ZARR_False_gzip_0/artifacts/metrics/Indices_Context.TRAINING_GR0.zarr": {"prov-ml:artifact_path": "prov/MetricsType.ZARR_False_gzip_0/artifacts/metrics/Indices_Context.TRAINING_GR0.zarr"}, "prov/MetricsType.ZARR_False_gzip_0/artifacts/metrics/Indices2_Context.TRAINING_GR0.zarr": {"prov-ml:artifact_path": "prov/MetricsType.ZARR_False_gzip_0/artifacts/metrics/Indices2_Context.TRAINING_GR0.zarr"}, "prov/MetricsType.ZARR_False_gzip_0/artifacts/metrics/Indices3_Context.TRAINING_GR0.zarr": {"prov-ml:artifact_path": "prov/MetricsType.ZARR_False_gzip_0/artifacts/metrics/Indices3_Context.TRAINING_GR0.zarr"}, "prov/MetricsType.ZARR_False_gzip_0/artifacts/metrics/Indices4_Context.TRAINING_GR0.zarr": {"prov-ml:artifact_path": "prov/MetricsType.ZARR_False_gzip_0/artifacts/metrics/Indices4_Context.TRAINING_GR0.zarr"}, "prov/MetricsType.ZARR_False_gzip_0/artifacts/metrics/Indices5_Context.TRAINING_GR0.zarr": {"prov-ml:artifact_path": "prov/MetricsType.ZARR_False_gzip_0/artifacts/metrics/Indices5_Context.TRAINING_GR0.zarr"}, "prov/MetricsType.ZARR_False_gzip_0/artifacts/metrics/MSE_test_Context.EVALUATION_GR0.zarr": {"prov-ml:artifact_path": "prov/MetricsType.ZARR_False_gzip_0/artifacts/metrics/MSE_test_Context.EVALUATION_GR0.zarr"}, "prov/MetricsType.ZARR_False_zstd_0/artifacts/mnist_model_version_0/mnist_model_version_0_0.pth": {"prov-ml:artifact_path": "prov/MetricsType.ZARR_False_zstd_0/artifacts/mnist_model_version_0/mnist_model_version_0_0.pth"}, "prov/MetricsType.ZARR_False_zstd_0/artifacts/mnist_model_version_1/mnist_model_version_1_0.pth": {"prov-ml:artifact_path": "prov/MetricsType.ZARR_False_zstd_0/artifacts/mnist_model_version_1/mnist_model_version_1_0.pth"}, "prov/MetricsType.ZARR_False_zstd_0/artifacts/mnist_model_version_2/mnist_model_version_2_0.pth": {"prov-ml:artifact_path": "prov/MetricsType.ZARR_False_zstd_0/artifacts/mnist_model_version_2/mnist_model_version_2_0.pth"}, "prov/MetricsType.ZARR_False_zstd_0/artifacts/mnist_model_version_3/mnist_model_version_3_0.pth": {"prov-ml:artifact_path": "prov/MetricsType.ZARR_False_zstd_0/artifacts/mnist_model_version_3/mnist_model_version_3_0.pth"}, "prov/MetricsType.ZARR_False_zstd_0/artifacts/mnist_model_version_4/mnist_model_version_4_0.pth": {"prov-ml:artifact_path": "prov/MetricsType.ZARR_False_zstd_0/artifacts/mnist_model_version_4/mnist_model_version_4_0.pth"}, "prov/MetricsType.ZARR_False_zstd_0/artifacts/metrics/MSE_train_Context.TRAINING_GR0.zarr": {"prov-ml:artifact_path": "prov/MetricsType.ZARR_False_zstd_0/artifacts/metrics/MSE_train_Context.TRAINING_GR0.zarr"}, "prov/MetricsType.ZARR_False_zstd_0/artifacts/metrics/MSE_train2_Context.TRAINING_GR0.zarr": {"prov-ml:artifact_path": "prov/MetricsType.ZARR_False_zstd_0/artifacts/metrics/MSE_train2_Context.TRAINING_GR0.zarr"}, "prov/MetricsType.ZARR_False_zstd_0/artifacts/metrics/MSE_train3_Context.TRAINING_GR0.zarr": {"prov-ml:artifact_path": "prov/MetricsType.ZARR_False_zstd_0/artifacts/metrics/MSE_train3_Context.TRAINING_GR0.zarr"}, "prov/MetricsType.ZARR_False_zstd_0/artifacts/metrics/MSE_train4_Context.TRAINING_GR0.zarr": {"prov-ml:artifact_path": "prov/MetricsType.ZARR_False_zstd_0/artifacts/metrics/MSE_train4_Context.TRAINING_GR0.zarr"}, "prov/MetricsType.ZARR_False_zstd_0/artifacts/metrics/MSE_train5_Context.TRAINING_GR0.zarr": {"prov-ml:artifact_path": "prov/MetricsType.ZARR_False_zstd_0/artifacts/metrics/MSE_train5_Context.TRAINING_GR0.zarr"}, "prov/MetricsType.ZARR_False_zstd_0/artifacts/metrics/Indices_Context.TRAINING_GR0.zarr": {"prov-ml:artifact_path": "prov/MetricsType.ZARR_False_zstd_0/artifacts/metrics/Indices_Context.TRAINING_GR0.zarr"}, "prov/MetricsType.ZARR_False_zstd_0/artifacts/metrics/Indices2_Context.TRAINING_GR0.zarr": {"prov-ml:artifact_path": "prov/MetricsType.ZARR_False_zstd_0/artifacts/metrics/Indices2_Context.TRAINING_GR0.zarr"}, "prov/MetricsType.ZARR_False_zstd_0/artifacts/metrics/Indices3_Context.TRAINING_GR0.zarr": {"prov-ml:artifact_path": "prov/MetricsType.ZARR_False_zstd_0/artifacts/metrics/Indices3_Context.TRAINING_GR0.zarr"}, "prov/MetricsType.ZARR_False_zstd_0/artifacts/metrics/Indices4_Context.TRAINING_GR0.zarr": {"prov-ml:artifact_path": "prov/MetricsType.ZARR_False_zstd_0/artifacts/metrics/Indices4_Context.TRAINING_GR0.zarr"}, "prov/MetricsType.ZARR_False_zstd_0/artifacts/metrics/Indices5_Context.TRAINING_GR0.zarr": {"prov-ml:artifact_path": "prov/MetricsType.ZARR_False_zstd_0/artifacts/metrics/Indices5_Context.TRAINING_GR0.zarr"}, "prov/MetricsType.ZARR_False_zstd_0/artifacts/metrics/MSE_test_Context.EVALUATION_GR0.zarr": {"prov-ml:artifact_path": "prov/MetricsType.ZARR_False_zstd_0/artifacts/metrics/MSE_test_Context.EVALUATION_GR0.zarr"}}, "activity": {"MetricsType.ZARR_False_zstd_execution": {"prov-ml:type": "LearningExecution"}, "epoch_0": {"prov-ml:type": "TrainingExecution"}, "epoch_1": {"prov-ml:type": "TrainingExecution"}, "epoch_2": {"prov-ml:type": "TrainingExecution"}, "epoch_3": {"prov-ml:type": "TrainingExecution"}, "epoch_4": {"prov-ml:type": "TrainingExecution"}, "test": {"prov-ml:type": "TestingExecution"}, "prov-ml:ModelRegistration": {}}, "agent": {"gabriele.padovani": {}}, "wasAssociatedWith": {"_:id1": {"prov:activity": "MetricsType.ZARR_False_zstd_execution", "prov:agent": "gabriele.padovani"}}, "used": {"_:id2": {"prov:activity": "MetricsType.ZARR_False_zstd_execution", "prov:entity": "source_code"}, "_:id11": {"prov:activity": "MetricsType.ZARR_False_zstd_execution", "prov:entity": "execution_start_time"}, "_:id12": {"prov:activity": "MetricsType.ZARR_False_zstd_execution", "prov:entity": "model_name"}, "_:id13": {"prov:activity": "MetricsType.ZARR_False_zstd_execution", "prov:entity": "total_params"}, "_:id14": {"prov:activity": "MetricsType.ZARR_False_zstd_execution", "prov:entity": "memory_of_model"}, "_:id15": {"prov:activity": "MetricsType.ZARR_False_zstd_execution", "prov:entity": "total_memory_load_of_model"}, "_:id16": {"prov:activity": "MetricsType.ZARR_False_zstd_execution", "prov:entity": "execution_end_time"}, "_:id18": {"prov:activity": "MetricsType.ZARR_False_zstd_execution", "prov:entity": "train_dataset"}}, "hadMember": {"_:id3": {"prov:collection": "MetricsType.ZARR_False_zstd", "prov:entity": "MetricsType.ZARR_False_zstd"}, "_:id19": {"prov:collection": "datasets", "prov:entity": "train_dataset"}, "_:id23": {"prov:collection": "prov/MetricsType.ZARR_False_zstd_0/artifacts/mnist_model_final/mnist_model_final_0.pth", "prov:entity": "prov/MetricsType.ZARR_False_blosc_lz4_0/artifacts/mnist_model_version_0/mnist_model_version_0_0.pth"}, "_:id24": {"prov:collection": "prov/MetricsType.ZARR_False_zstd_0/artifacts/mnist_model_final/mnist_model_final_0.pth", "prov:entity": "prov/MetricsType.ZARR_False_blosc_lz4_0/artifacts/mnist_model_version_1/mnist_model_version_1_0.pth"}, "_:id25": {"prov:collection": "prov/MetricsType.ZARR_False_zstd_0/artifacts/mnist_model_final/mnist_model_final_0.pth", "prov:entity": "prov/MetricsType.ZARR_False_blosc_lz4_0/artifacts/mnist_model_version_2/mnist_model_version_2_0.pth"}, "_:id26": {"prov:collection": "prov/MetricsType.ZARR_False_zstd_0/artifacts/mnist_model_final/mnist_model_final_0.pth", "prov:entity": "prov/MetricsType.ZARR_False_blosc_lz4_0/artifacts/mnist_model_version_3/mnist_model_version_3_0.pth"}, "_:id27": {"prov:collection": "prov/MetricsType.ZARR_False_zstd_0/artifacts/mnist_model_final/mnist_model_final_0.pth", "prov:entity": "prov/MetricsType.ZARR_False_blosc_lz4_0/artifacts/mnist_model_version_4/mnist_model_version_4_0.pth"}, "_:id28": {"prov:collection": "prov/MetricsType.ZARR_False_zstd_0/artifacts/mnist_model_final/mnist_model_final_0.pth", "prov:entity": "prov/MetricsType.ZARR_False_blosc_lz4_0/artifacts/mnist_model_final/mnist_model_final_0.pth"}, "_:id29": {"prov:collection": "prov/MetricsType.ZARR_False_zstd_0/artifacts/mnist_model_final/mnist_model_final_0.pth", "prov:entity": "prov/MetricsType.ZARR_False_blosc_lz4hc_0/artifacts/mnist_model_version_0/mnist_model_version_0_0.pth"}, "_:id30": {"prov:collection": "prov/MetricsType.ZARR_False_zstd_0/artifacts/mnist_model_final/mnist_model_final_0.pth", "prov:entity": "prov/MetricsType.ZARR_False_blosc_lz4hc_0/artifacts/mnist_model_version_1/mnist_model_version_1_0.pth"}, "_:id31": {"prov:collection": "prov/MetricsType.ZARR_False_zstd_0/artifacts/mnist_model_final/mnist_model_final_0.pth", "prov:entity": "prov/MetricsType.ZARR_False_blosc_lz4hc_0/artifacts/mnist_model_version_2/mnist_model_version_2_0.pth"}, "_:id32": {"prov:collection": "prov/MetricsType.ZARR_False_zstd_0/artifacts/mnist_model_final/mnist_model_final_0.pth", "prov:entity": "prov/MetricsType.ZARR_False_blosc_lz4hc_0/artifacts/mnist_model_version_3/mnist_model_version_3_0.pth"}, "_:id33": {"prov:collection": "prov/MetricsType.ZARR_False_zstd_0/artifacts/mnist_model_final/mnist_model_final_0.pth", "prov:entity": "prov/MetricsType.ZARR_False_blosc_lz4hc_0/artifacts/mnist_model_version_4/mnist_model_version_4_0.pth"}, "_:id34": {"prov:collection": "prov/MetricsType.ZARR_False_zstd_0/artifacts/mnist_model_final/mnist_model_final_0.pth", "prov:entity": "prov/MetricsType.ZARR_False_blosc_lz4hc_0/artifacts/mnist_model_final/mnist_model_final_0.pth"}, "_:id35": {"prov:collection": "prov/MetricsType.ZARR_False_zstd_0/artifacts/mnist_model_final/mnist_model_final_0.pth", "prov:entity": "prov/MetricsType.ZARR_False_blosc_blosclz_0/artifacts/mnist_model_version_0/mnist_model_version_0_0.pth"}, "_:id36": {"prov:collection": "prov/MetricsType.ZARR_False_zstd_0/artifacts/mnist_model_final/mnist_model_final_0.pth", "prov:entity": "prov/MetricsType.ZARR_False_blosc_blosclz_0/artifacts/mnist_model_version_1/mnist_model_version_1_0.pth"}, "_:id37": {"prov:collection": "prov/MetricsType.ZARR_False_zstd_0/artifacts/mnist_model_final/mnist_model_final_0.pth", "prov:entity": "prov/MetricsType.ZARR_False_blosc_blosclz_0/artifacts/mnist_model_version_2/mnist_model_version_2_0.pth"}, "_:id38": {"prov:collection": "prov/MetricsType.ZARR_False_zstd_0/artifacts/mnist_model_final/mnist_model_final_0.pth", "prov:entity": "prov/MetricsType.ZARR_False_blosc_blosclz_0/artifacts/mnist_model_version_3/mnist_model_version_3_0.pth"}, "_:id39": {"prov:collection": "prov/MetricsType.ZARR_False_zstd_0/artifacts/mnist_model_final/mnist_model_final_0.pth", "prov:entity": "prov/MetricsType.ZARR_False_blosc_blosclz_0/artifacts/mnist_model_version_4/mnist_model_version_4_0.pth"}, "_:id40": {"prov:collection": "prov/MetricsType.ZARR_False_zstd_0/artifacts/mnist_model_final/mnist_model_final_0.pth", "prov:entity": "prov/MetricsType.ZARR_False_blosc_blosclz_0/artifacts/mnist_model_final/mnist_model_final_0.pth"}, "_:id41": {"prov:collection": "prov/MetricsType.ZARR_False_zstd_0/artifacts/mnist_model_final/mnist_model_final_0.pth", "prov:entity": "prov/MetricsType.ZARR_False_blosc_zstd_0/artifacts/mnist_model_version_0/mnist_model_version_0_0.pth"}, "_:id42": {"prov:collection": "prov/MetricsType.ZARR_False_zstd_0/artifacts/mnist_model_final/mnist_model_final_0.pth", "prov:entity": "prov/MetricsType.ZARR_False_blosc_zstd_0/artifacts/mnist_model_version_1/mnist_model_version_1_0.pth"}, "_:id43": {"prov:collection": "prov/MetricsType.ZARR_False_zstd_0/artifacts/mnist_model_final/mnist_model_final_0.pth", "prov:entity": "prov/MetricsType.ZARR_False_blosc_zstd_0/artifacts/mnist_model_version_2/mnist_model_version_2_0.pth"}, "_:id44": {"prov:collection": "prov/MetricsType.ZARR_False_zstd_0/artifacts/mnist_model_final/mnist_model_final_0.pth", "prov:entity": "prov/MetricsType.ZARR_False_blosc_zstd_0/artifacts/mnist_model_version_3/mnist_model_version_3_0.pth"}, "_:id45": {"prov:collection": "prov/MetricsType.ZARR_False_zstd_0/artifacts/mnist_model_final/mnist_model_final_0.pth", "prov:entity": "prov/MetricsType.ZARR_False_blosc_zstd_0/artifacts/mnist_model_version_4/mnist_model_version_4_0.pth"}, "_:id46": {"prov:collection": "prov/MetricsType.ZARR_False_zstd_0/artifacts/mnist_model_final/mnist_model_final_0.pth", "prov:entity": "prov/MetricsType.ZARR_False_blosc_zstd_0/artifacts/mnist_model_final/mnist_model_final_0.pth"}, "_:id47": {"prov:collection": "prov/MetricsType.ZARR_False_zstd_0/artifacts/mnist_model_final/mnist_model_final_0.pth", "prov:entity": "prov/MetricsType.ZARR_False_blosc_zlib_0/artifacts/mnist_model_version_0/mnist_model_version_0_0.pth"}, "_:id48": {"prov:collection": "prov/MetricsType.ZARR_False_zstd_0/artifacts/mnist_model_final/mnist_model_final_0.pth", "prov:entity": "prov/MetricsType.ZARR_False_blosc_zlib_0/artifacts/mnist_model_version_1/mnist_model_version_1_0.pth"}, "_:id49": {"prov:collection": "prov/MetricsType.ZARR_False_zstd_0/artifacts/mnist_model_final/mnist_model_final_0.pth", "prov:entity": "prov/MetricsType.ZARR_False_blosc_zlib_0/artifacts/mnist_model_version_2/mnist_model_version_2_0.pth"}, "_:id50": {"prov:collection": "prov/MetricsType.ZARR_False_zstd_0/artifacts/mnist_model_final/mnist_model_final_0.pth", "prov:entity": "prov/MetricsType.ZARR_False_blosc_zlib_0/artifacts/mnist_model_version_3/mnist_model_version_3_0.pth"}, "_:id51": {"prov:collection": "prov/MetricsType.ZARR_False_zstd_0/artifacts/mnist_model_final/mnist_model_final_0.pth", "prov:entity": "prov/MetricsType.ZARR_False_blosc_zlib_0/artifacts/mnist_model_version_4/mnist_model_version_4_0.pth"}, "_:id52": {"prov:collection": "prov/MetricsType.ZARR_False_zstd_0/artifacts/mnist_model_final/mnist_model_final_0.pth", "prov:entity": "prov/MetricsType.ZARR_False_blosc_zlib_0/artifacts/mnist_model_final/mnist_model_final_0.pth"}, "_:id53": {"prov:collection": "prov/MetricsType.ZARR_False_zstd_0/artifacts/mnist_model_final/mnist_model_final_0.pth", "prov:entity": "prov/MetricsType.ZARR_False_gzip_0/artifacts/mnist_model_version_0/mnist_model_version_0_0.pth"}, "_:id54": {"prov:collection": "prov/MetricsType.ZARR_False_zstd_0/artifacts/mnist_model_final/mnist_model_final_0.pth", "prov:entity": "prov/MetricsType.ZARR_False_gzip_0/artifacts/mnist_model_version_1/mnist_model_version_1_0.pth"}, "_:id55": {"prov:collection": "prov/MetricsType.ZARR_False_zstd_0/artifacts/mnist_model_final/mnist_model_final_0.pth", "prov:entity": "prov/MetricsType.ZARR_False_gzip_0/artifacts/mnist_model_version_2/mnist_model_version_2_0.pth"}, "_:id56": {"prov:collection": "prov/MetricsType.ZARR_False_zstd_0/artifacts/mnist_model_final/mnist_model_final_0.pth", "prov:entity": "prov/MetricsType.ZARR_False_gzip_0/artifacts/mnist_model_version_3/mnist_model_version_3_0.pth"}, "_:id57": {"prov:collection": "prov/MetricsType.ZARR_False_zstd_0/artifacts/mnist_model_final/mnist_model_final_0.pth", "prov:entity": "prov/MetricsType.ZARR_False_gzip_0/artifacts/mnist_model_version_4/mnist_model_version_4_0.pth"}, "_:id58": {"prov:collection": "prov/MetricsType.ZARR_False_zstd_0/artifacts/mnist_model_final/mnist_model_final_0.pth", "prov:entity": "prov/MetricsType.ZARR_False_gzip_0/artifacts/mnist_model_final/mnist_model_final_0.pth"}, "_:id59": {"prov:collection": "prov/MetricsType.ZARR_False_zstd_0/artifacts/mnist_model_final/mnist_model_final_0.pth", "prov:entity": "prov/MetricsType.ZARR_False_zstd_0/artifacts/mnist_model_version_0/mnist_model_version_0_0.pth"}, "_:id60": {"prov:collection": "prov/MetricsType.ZARR_False_zstd_0/artifacts/mnist_model_final/mnist_model_final_0.pth", "prov:entity": "prov/MetricsType.ZARR_False_zstd_0/artifacts/mnist_model_version_1/mnist_model_version_1_0.pth"}, "_:id61": {"prov:collection": "prov/MetricsType.ZARR_False_zstd_0/artifacts/mnist_model_final/mnist_model_final_0.pth", "prov:entity": "prov/MetricsType.ZARR_False_zstd_0/artifacts/mnist_model_version_2/mnist_model_version_2_0.pth"}, "_:id62": {"prov:collection": "prov/MetricsType.ZARR_False_zstd_0/artifacts/mnist_model_final/mnist_model_final_0.pth", "prov:entity": "prov/MetricsType.ZARR_False_zstd_0/artifacts/mnist_model_version_3/mnist_model_version_3_0.pth"}, "_:id63": {"prov:collection": "prov/MetricsType.ZARR_False_zstd_0/artifacts/mnist_model_final/mnist_model_final_0.pth", "prov:entity": "prov/MetricsType.ZARR_False_zstd_0/artifacts/mnist_model_version_4/mnist_model_version_4_0.pth"}}, "wasGeneratedBy": {"_:id4": {"prov:entity": "MetricsType.ZARR_False_zstd", "prov:activity": "MetricsType.ZARR_False_zstd_execution"}, "MSE_train_train_0_gen": {"prov:entity": "MSE_train_Context.TRAINING", "prov:activity": "epoch_0"}, "MSE_train_train_1_gen": {"prov:entity": "MSE_train_Context.TRAINING", "prov:activity": "epoch_1"}, "MSE_train_train_2_gen": {"prov:entity": "MSE_train_Context.TRAINING", "prov:activity": "epoch_2"}, "MSE_train_train_3_gen": {"prov:entity": "MSE_train_Context.TRAINING", "prov:activity": "epoch_3"}, "MSE_train_train_4_gen": {"prov:entity": "MSE_train_Context.TRAINING", "prov:activity": "epoch_4"}, "MSE_train2_train_0_gen": {"prov:entity": "MSE_train2_Context.TRAINING", "prov:activity": "epoch_0"}, "MSE_train2_train_1_gen": {"prov:entity": "MSE_train2_Context.TRAINING", "prov:activity": "epoch_1"}, "MSE_train2_train_2_gen": {"prov:entity": "MSE_train2_Context.TRAINING", "prov:activity": "epoch_2"}, "MSE_train2_train_3_gen": {"prov:entity": "MSE_train2_Context.TRAINING", "prov:activity": "epoch_3"}, "MSE_train2_train_4_gen": {"prov:entity": "MSE_train2_Context.TRAINING", "prov:activity": "epoch_4"}, "MSE_train3_train_0_gen": {"prov:entity": "MSE_train3_Context.TRAINING", "prov:activity": "epoch_0"}, "MSE_train3_train_1_gen": {"prov:entity": "MSE_train3_Context.TRAINING", "prov:activity": "epoch_1"}, "MSE_train3_train_2_gen": {"prov:entity": "MSE_train3_Context.TRAINING", "prov:activity": "epoch_2"}, "MSE_train3_train_3_gen": {"prov:entity": "MSE_train3_Context.TRAINING", "prov:activity": "epoch_3"}, "MSE_train3_train_4_gen": {"prov:entity": "MSE_train3_Context.TRAINING", "prov:activity": "epoch_4"}, "MSE_train4_train_0_gen": {"prov:entity": "MSE_train4_Context.TRAINING", "prov:activity": "epoch_0"}, "MSE_train4_train_1_gen": {"prov:entity": "MSE_train4_Context.TRAINING", "prov:activity": "epoch_1"}, "MSE_train4_train_2_gen": {"prov:entity": "MSE_train4_Context.TRAINING", "prov:activity": "epoch_2"}, "MSE_train4_train_3_gen": {"prov:entity": "MSE_train4_Context.TRAINING", "prov:activity": "epoch_3"}, "MSE_train4_train_4_gen": {"prov:entity": "MSE_train4_Context.TRAINING", "prov:activity": "epoch_4"}, "MSE_train5_train_0_gen": {"prov:entity": "MSE_train5_Context.TRAINING", "prov:activity": "epoch_0"}, "MSE_train5_train_1_gen": {"prov:entity": "MSE_train5_Context.TRAINING", "prov:activity": "epoch_1"}, "MSE_train5_train_2_gen": {"prov:entity": "MSE_train5_Context.TRAINING", "prov:activity": "epoch_2"}, "MSE_train5_train_3_gen": {"prov:entity": "MSE_train5_Context.TRAINING", "prov:activity": "epoch_3"}, "MSE_train5_train_4_gen": {"prov:entity": "MSE_train5_Context.TRAINING", "prov:activity": "epoch_4"}, "Indices_train_0_gen": {"prov:entity": "Indices_Context.TRAINING", "prov:activity": "epoch_0"}, "Indices_train_1_gen": {"prov:entity": "Indices_Context.TRAINING", "prov:activity": "epoch_1"}, "Indices_train_2_gen": {"prov:entity": "Indices_Context.TRAINING", "prov:activity": "epoch_2"}, "Indices_train_3_gen": {"prov:entity": "Indices_Context.TRAINING", "prov:activity": "epoch_3"}, "Indices_train_4_gen": {"prov:entity": "Indices_Context.TRAINING", "prov:activity": "epoch_4"}, "Indices2_train_0_gen": {"prov:entity": "Indices2_Context.TRAINING", "prov:activity": "epoch_0"}, "Indices2_train_1_gen": {"prov:entity": "Indices2_Context.TRAINING", "prov:activity": "epoch_1"}, "Indices2_train_2_gen": {"prov:entity": "Indices2_Context.TRAINING", "prov:activity": "epoch_2"}, "Indices2_train_3_gen": {"prov:entity": "Indices2_Context.TRAINING", "prov:activity": "epoch_3"}, "Indices2_train_4_gen": {"prov:entity": "Indices2_Context.TRAINING", "prov:activity": "epoch_4"}, "Indices3_train_0_gen": {"prov:entity": "Indices3_Context.TRAINING", "prov:activity": "epoch_0"}, "Indices3_train_1_gen": {"prov:entity": "Indices3_Context.TRAINING", "prov:activity": "epoch_1"}, "Indices3_train_2_gen": {"prov:entity": "Indices3_Context.TRAINING", "prov:activity": "epoch_2"}, "Indices3_train_3_gen": {"prov:entity": "Indices3_Context.TRAINING", "prov:activity": "epoch_3"}, "Indices3_train_4_gen": {"prov:entity": "Indices3_Context.TRAINING", "prov:activity": "epoch_4"}, "Indices4_train_0_gen": {"prov:entity": "Indices4_Context.TRAINING", "prov:activity": "epoch_0"}, "Indices4_train_1_gen": {"prov:entity": "Indices4_Context.TRAINING", "prov:activity": "epoch_1"}, "Indices4_train_2_gen": {"prov:entity": "Indices4_Context.TRAINING", "prov:activity": "epoch_2"}, "Indices4_train_3_gen": {"prov:entity": "Indices4_Context.TRAINING", "prov:activity": "epoch_3"}, "Indices4_train_4_gen": {"prov:entity": "Indices4_Context.TRAINING", "prov:activity": "epoch_4"}, "Indices5_train_0_gen": {"prov:entity": "Indices5_Context.TRAINING", "prov:activity": "epoch_0"}, "Indices5_train_1_gen": {"prov:entity": "Indices5_Context.TRAINING", "prov:activity": "epoch_1"}, "Indices5_train_2_gen": {"prov:entity": "Indices5_Context.TRAINING", "prov:activity": "epoch_2"}, "Indices5_train_3_gen": {"prov:entity": "Indices5_Context.TRAINING", "prov:activity": "epoch_3"}, "Indices5_train_4_gen": {"prov:entity": "Indices5_Context.TRAINING", "prov:activity": "epoch_4"}, "test_gen": {"prov:entity": "MSE_test_Context.EVALUATION", "prov:activity": "test"}, "_:id17": {"prov:entity": "final_run_statistics", "prov:activity": "MetricsType.ZARR_False_zstd_execution"}, "_:id20": {"prov:entity": "datasets", "prov:activity": "MetricsType.ZARR_False_zstd_execution"}, "prov/MetricsType.ZARR_False_zstd_0/artifacts/mnist_model_final/mnist_model_final_0.pth_gen": {"prov:entity": "prov/MetricsType.ZARR_False_zstd_0/artifacts/mnist_model_final/mnist_model_final_0.pth", "prov:activity": "MetricsType.ZARR_False_zstd_execution"}, "_:id22": [{"prov:entity": "prov/MetricsType.ZARR_False_zstd_0/artifacts/mnist_model_final/mnist_model_final_0.pth", "prov:activity": "prov-ml:ModelRegistration"}, {"prov:entity": "prov/MetricsType.ZARR_False_zstd_0/artifacts/mnist_model_final/mnist_model_final_0.pth", "prov:activity": "prov-ml:ModelRegistration"}], "_:id64": {"prov:entity": "prov/MetricsType.ZARR_False_blosc_lz4_0/artifacts/mnist_model_version_0/mnist_model_version_0_0.pth", "prov:activity": "prov-ml:ModelRegistration"}, "_:id65": {"prov:entity": "prov/MetricsType.ZARR_False_blosc_lz4_0/artifacts/mnist_model_version_1/mnist_model_version_1_0.pth", "prov:activity": "prov-ml:ModelRegistration"}, "_:id66": {"prov:entity": "prov/MetricsType.ZARR_False_blosc_lz4_0/artifacts/mnist_model_version_2/mnist_model_version_2_0.pth", "prov:activity": "prov-ml:ModelRegistration"}, "_:id67": {"prov:entity": "prov/MetricsType.ZARR_False_blosc_lz4_0/artifacts/mnist_model_version_3/mnist_model_version_3_0.pth", "prov:activity": "prov-ml:ModelRegistration"}, "_:id68": {"prov:entity": "prov/MetricsType.ZARR_False_blosc_lz4_0/artifacts/mnist_model_version_4/mnist_model_version_4_0.pth", "prov:activity": "prov-ml:ModelRegistration"}, "_:id69": {"prov:entity": "prov/MetricsType.ZARR_False_blosc_lz4_0/artifacts/mnist_model_final/mnist_model_final_0.pth", "prov:activity": "prov-ml:ModelRegistration"}, "prov/MetricsType.ZARR_False_blosc_lz4_0/artifacts/metrics/MSE_train_Context.TRAINING_GR0.zarr_gen": {"prov:entity": "prov/MetricsType.ZARR_False_blosc_lz4_0/artifacts/metrics/MSE_train_Context.TRAINING_GR0.zarr", "prov:activity": "MetricsType.ZARR_False_zstd_execution"}, "prov/MetricsType.ZARR_False_blosc_lz4_0/artifacts/metrics/MSE_train2_Context.TRAINING_GR0.zarr_gen": {"prov:entity": "prov/MetricsType.ZARR_False_blosc_lz4_0/artifacts/metrics/MSE_train2_Context.TRAINING_GR0.zarr", "prov:activity": "MetricsType.ZARR_False_zstd_execution"}, "prov/MetricsType.ZARR_False_blosc_lz4_0/artifacts/metrics/MSE_train3_Context.TRAINING_GR0.zarr_gen": {"prov:entity": "prov/MetricsType.ZARR_False_blosc_lz4_0/artifacts/metrics/MSE_train3_Context.TRAINING_GR0.zarr", "prov:activity": "MetricsType.ZARR_False_zstd_execution"}, "prov/MetricsType.ZARR_False_blosc_lz4_0/artifacts/metrics/MSE_train4_Context.TRAINING_GR0.zarr_gen": {"prov:entity": "prov/MetricsType.ZARR_False_blosc_lz4_0/artifacts/metrics/MSE_train4_Context.TRAINING_GR0.zarr", "prov:activity": "MetricsType.ZARR_False_zstd_execution"}, "prov/MetricsType.ZARR_False_blosc_lz4_0/artifacts/metrics/MSE_train5_Context.TRAINING_GR0.zarr_gen": {"prov:entity": "prov/MetricsType.ZARR_False_blosc_lz4_0/artifacts/metrics/MSE_train5_Context.TRAINING_GR0.zarr", "prov:activity": "MetricsType.ZARR_False_zstd_execution"}, "prov/MetricsType.ZARR_False_blosc_lz4_0/artifacts/metrics/Indices_Context.TRAINING_GR0.zarr_gen": {"prov:entity": "prov/MetricsType.ZARR_False_blosc_lz4_0/artifacts/metrics/Indices_Context.TRAINING_GR0.zarr", "prov:activity": "MetricsType.ZARR_False_zstd_execution"}, "prov/MetricsType.ZARR_False_blosc_lz4_0/artifacts/metrics/Indices2_Context.TRAINING_GR0.zarr_gen": {"prov:entity": "prov/MetricsType.ZARR_False_blosc_lz4_0/artifacts/metrics/Indices2_Context.TRAINING_GR0.zarr", "prov:activity": "MetricsType.ZARR_False_zstd_execution"}, "prov/MetricsType.ZARR_False_blosc_lz4_0/artifacts/metrics/Indices3_Context.TRAINING_GR0.zarr_gen": {"prov:entity": "prov/MetricsType.ZARR_False_blosc_lz4_0/artifacts/metrics/Indices3_Context.TRAINING_GR0.zarr", "prov:activity": "MetricsType.ZARR_False_zstd_execution"}, "prov/MetricsType.ZARR_False_blosc_lz4_0/artifacts/metrics/Indices4_Context.TRAINING_GR0.zarr_gen": {"prov:entity": "prov/MetricsType.ZARR_False_blosc_lz4_0/artifacts/metrics/Indices4_Context.TRAINING_GR0.zarr", "prov:activity": "MetricsType.ZARR_False_zstd_execution"}, "prov/MetricsType.ZARR_False_blosc_lz4_0/artifacts/metrics/Indices5_Context.TRAINING_GR0.zarr_gen": {"prov:entity": "prov/MetricsType.ZARR_False_blosc_lz4_0/artifacts/metrics/Indices5_Context.TRAINING_GR0.zarr", "prov:activity": "MetricsType.ZARR_False_zstd_execution"}, "prov/MetricsType.ZARR_False_blosc_lz4_0/artifacts/metrics/MSE_test_Context.EVALUATION_GR0.zarr_gen": {"prov:entity": "prov/MetricsType.ZARR_False_blosc_lz4_0/artifacts/metrics/MSE_test_Context.EVALUATION_GR0.zarr", "prov:activity": "MetricsType.ZARR_False_zstd_execution"}, "_:id70": {"prov:entity": "prov/MetricsType.ZARR_False_blosc_lz4hc_0/artifacts/mnist_model_version_0/mnist_model_version_0_0.pth", "prov:activity": "prov-ml:ModelRegistration"}, "_:id71": {"prov:entity": "prov/MetricsType.ZARR_False_blosc_lz4hc_0/artifacts/mnist_model_version_1/mnist_model_version_1_0.pth", "prov:activity": "prov-ml:ModelRegistration"}, "_:id72": {"prov:entity": "prov/MetricsType.ZARR_False_blosc_lz4hc_0/artifacts/mnist_model_version_2/mnist_model_version_2_0.pth", "prov:activity": "prov-ml:ModelRegistration"}, "_:id73": {"prov:entity": "prov/MetricsType.ZARR_False_blosc_lz4hc_0/artifacts/mnist_model_version_3/mnist_model_version_3_0.pth", "prov:activity": "prov-ml:ModelRegistration"}, "_:id74": {"prov:entity": "prov/MetricsType.ZARR_False_blosc_lz4hc_0/artifacts/mnist_model_version_4/mnist_model_version_4_0.pth", "prov:activity": "prov-ml:ModelRegistration"}, "_:id75": {"prov:entity": "prov/MetricsType.ZARR_False_blosc_lz4hc_0/artifacts/mnist_model_final/mnist_model_final_0.pth", "prov:activity": "prov-ml:ModelRegistration"}, "prov/MetricsType.ZARR_False_blosc_lz4hc_0/artifacts/metrics/MSE_train_Context.TRAINING_GR0.zarr_gen": {"prov:entity": "prov/MetricsType.ZARR_False_blosc_lz4hc_0/artifacts/metrics/MSE_train_Context.TRAINING_GR0.zarr", "prov:activity": "MetricsType.ZARR_False_zstd_execution"}, "prov/MetricsType.ZARR_False_blosc_lz4hc_0/artifacts/metrics/MSE_train2_Context.TRAINING_GR0.zarr_gen": {"prov:entity": "prov/MetricsType.ZARR_False_blosc_lz4hc_0/artifacts/metrics/MSE_train2_Context.TRAINING_GR0.zarr", "prov:activity": "MetricsType.ZARR_False_zstd_execution"}, "prov/MetricsType.ZARR_False_blosc_lz4hc_0/artifacts/metrics/MSE_train3_Context.TRAINING_GR0.zarr_gen": {"prov:entity": "prov/MetricsType.ZARR_False_blosc_lz4hc_0/artifacts/metrics/MSE_train3_Context.TRAINING_GR0.zarr", "prov:activity": "MetricsType.ZARR_False_zstd_execution"}, "prov/MetricsType.ZARR_False_blosc_lz4hc_0/artifacts/metrics/MSE_train4_Context.TRAINING_GR0.zarr_gen": {"prov:entity": "prov/MetricsType.ZARR_False_blosc_lz4hc_0/artifacts/metrics/MSE_train4_Context.TRAINING_GR0.zarr", "prov:activity": "MetricsType.ZARR_False_zstd_execution"}, "prov/MetricsType.ZARR_False_blosc_lz4hc_0/artifacts/metrics/MSE_train5_Context.TRAINING_GR0.zarr_gen": {"prov:entity": "prov/MetricsType.ZARR_False_blosc_lz4hc_0/artifacts/metrics/MSE_train5_Context.TRAINING_GR0.zarr", "prov:activity": "MetricsType.ZARR_False_zstd_execution"}, "prov/MetricsType.ZARR_False_blosc_lz4hc_0/artifacts/metrics/Indices_Context.TRAINING_GR0.zarr_gen": {"prov:entity": "prov/MetricsType.ZARR_False_blosc_lz4hc_0/artifacts/metrics/Indices_Context.TRAINING_GR0.zarr", "prov:activity": "MetricsType.ZARR_False_zstd_execution"}, "prov/MetricsType.ZARR_False_blosc_lz4hc_0/artifacts/metrics/Indices2_Context.TRAINING_GR0.zarr_gen": {"prov:entity": "prov/MetricsType.ZARR_False_blosc_lz4hc_0/artifacts/metrics/Indices2_Context.TRAINING_GR0.zarr", "prov:activity": "MetricsType.ZARR_False_zstd_execution"}, "prov/MetricsType.ZARR_False_blosc_lz4hc_0/artifacts/metrics/Indices3_Context.TRAINING_GR0.zarr_gen": {"prov:entity": "prov/MetricsType.ZARR_False_blosc_lz4hc_0/artifacts/metrics/Indices3_Context.TRAINING_GR0.zarr", "prov:activity": "MetricsType.ZARR_False_zstd_execution"}, "prov/MetricsType.ZARR_False_blosc_lz4hc_0/artifacts/metrics/Indices4_Context.TRAINING_GR0.zarr_gen": {"prov:entity": "prov/MetricsType.ZARR_False_blosc_lz4hc_0/artifacts/metrics/Indices4_Context.TRAINING_GR0.zarr", "prov:activity": "MetricsType.ZARR_False_zstd_execution"}, "prov/MetricsType.ZARR_False_blosc_lz4hc_0/artifacts/metrics/Indices5_Context.TRAINING_GR0.zarr_gen": {"prov:entity": "prov/MetricsType.ZARR_False_blosc_lz4hc_0/artifacts/metrics/Indices5_Context.TRAINING_GR0.zarr", "prov:activity": "MetricsType.ZARR_False_zstd_execution"}, "prov/MetricsType.ZARR_False_blosc_lz4hc_0/artifacts/metrics/MSE_test_Context.EVALUATION_GR0.zarr_gen": {"prov:entity": "prov/MetricsType.ZARR_False_blosc_lz4hc_0/artifacts/metrics/MSE_test_Context.EVALUATION_GR0.zarr", "prov:activity": "MetricsType.ZARR_False_zstd_execution"}, "_:id76": {"prov:entity": "prov/MetricsType.ZARR_False_blosc_blosclz_0/artifacts/mnist_model_version_0/mnist_model_version_0_0.pth", "prov:activity": "prov-ml:ModelRegistration"}, "_:id77": {"prov:entity": "prov/MetricsType.ZARR_False_blosc_blosclz_0/artifacts/mnist_model_version_1/mnist_model_version_1_0.pth", "prov:activity": "prov-ml:ModelRegistration"}, "_:id78": {"prov:entity": "prov/MetricsType.ZARR_False_blosc_blosclz_0/artifacts/mnist_model_version_2/mnist_model_version_2_0.pth", "prov:activity": "prov-ml:ModelRegistration"}, "_:id79": {"prov:entity": "prov/MetricsType.ZARR_False_blosc_blosclz_0/artifacts/mnist_model_version_3/mnist_model_version_3_0.pth", "prov:activity": "prov-ml:ModelRegistration"}, "_:id80": {"prov:entity": "prov/MetricsType.ZARR_False_blosc_blosclz_0/artifacts/mnist_model_version_4/mnist_model_version_4_0.pth", "prov:activity": "prov-ml:ModelRegistration"}, "_:id81": {"prov:entity": "prov/MetricsType.ZARR_False_blosc_blosclz_0/artifacts/mnist_model_final/mnist_model_final_0.pth", "prov:activity": "prov-ml:ModelRegistration"}, "prov/MetricsType.ZARR_False_blosc_blosclz_0/artifacts/metrics/MSE_train_Context.TRAINING_GR0.zarr_gen": {"prov:entity": "prov/MetricsType.ZARR_False_blosc_blosclz_0/artifacts/metrics/MSE_train_Context.TRAINING_GR0.zarr", "prov:activity": "MetricsType.ZARR_False_zstd_execution"}, "prov/MetricsType.ZARR_False_blosc_blosclz_0/artifacts/metrics/MSE_train2_Context.TRAINING_GR0.zarr_gen": {"prov:entity": "prov/MetricsType.ZARR_False_blosc_blosclz_0/artifacts/metrics/MSE_train2_Context.TRAINING_GR0.zarr", "prov:activity": "MetricsType.ZARR_False_zstd_execution"}, "prov/MetricsType.ZARR_False_blosc_blosclz_0/artifacts/metrics/MSE_train3_Context.TRAINING_GR0.zarr_gen": {"prov:entity": "prov/MetricsType.ZARR_False_blosc_blosclz_0/artifacts/metrics/MSE_train3_Context.TRAINING_GR0.zarr", "prov:activity": "MetricsType.ZARR_False_zstd_execution"}, "prov/MetricsType.ZARR_False_blosc_blosclz_0/artifacts/metrics/MSE_train4_Context.TRAINING_GR0.zarr_gen": {"prov:entity": "prov/MetricsType.ZARR_False_blosc_blosclz_0/artifacts/metrics/MSE_train4_Context.TRAINING_GR0.zarr", "prov:activity": "MetricsType.ZARR_False_zstd_execution"}, "prov/MetricsType.ZARR_False_blosc_blosclz_0/artifacts/metrics/MSE_train5_Context.TRAINING_GR0.zarr_gen": {"prov:entity": "prov/MetricsType.ZARR_False_blosc_blosclz_0/artifacts/metrics/MSE_train5_Context.TRAINING_GR0.zarr", "prov:activity": "MetricsType.ZARR_False_zstd_execution"}, "prov/MetricsType.ZARR_False_blosc_blosclz_0/artifacts/metrics/Indices_Context.TRAINING_GR0.zarr_gen": {"prov:entity": "prov/MetricsType.ZARR_False_blosc_blosclz_0/artifacts/metrics/Indices_Context.TRAINING_GR0.zarr", "prov:activity": "MetricsType.ZARR_False_zstd_execution"}, "prov/MetricsType.ZARR_False_blosc_blosclz_0/artifacts/metrics/Indices2_Context.TRAINING_GR0.zarr_gen": {"prov:entity": "prov/MetricsType.ZARR_False_blosc_blosclz_0/artifacts/metrics/Indices2_Context.TRAINING_GR0.zarr", "prov:activity": "MetricsType.ZARR_False_zstd_execution"}, "prov/MetricsType.ZARR_False_blosc_blosclz_0/artifacts/metrics/Indices3_Context.TRAINING_GR0.zarr_gen": {"prov:entity": "prov/MetricsType.ZARR_False_blosc_blosclz_0/artifacts/metrics/Indices3_Context.TRAINING_GR0.zarr", "prov:activity": "MetricsType.ZARR_False_zstd_execution"}, "prov/MetricsType.ZARR_False_blosc_blosclz_0/artifacts/metrics/Indices4_Context.TRAINING_GR0.zarr_gen": {"prov:entity": "prov/MetricsType.ZARR_False_blosc_blosclz_0/artifacts/metrics/Indices4_Context.TRAINING_GR0.zarr", "prov:activity": "MetricsType.ZARR_False_zstd_execution"}, "prov/MetricsType.ZARR_False_blosc_blosclz_0/artifacts/metrics/Indices5_Context.TRAINING_GR0.zarr_gen": {"prov:entity": "prov/MetricsType.ZARR_False_blosc_blosclz_0/artifacts/metrics/Indices5_Context.TRAINING_GR0.zarr", "prov:activity": "MetricsType.ZARR_False_zstd_execution"}, "prov/MetricsType.ZARR_False_blosc_blosclz_0/artifacts/metrics/MSE_test_Context.EVALUATION_GR0.zarr_gen": {"prov:entity": "prov/MetricsType.ZARR_False_blosc_blosclz_0/artifacts/metrics/MSE_test_Context.EVALUATION_GR0.zarr", "prov:activity": "MetricsType.ZARR_False_zstd_execution"}, "_:id82": {"prov:entity": "prov/MetricsType.ZARR_False_blosc_zstd_0/artifacts/mnist_model_version_0/mnist_model_version_0_0.pth", "prov:activity": "prov-ml:ModelRegistration"}, "_:id83": {"prov:entity": "prov/MetricsType.ZARR_False_blosc_zstd_0/artifacts/mnist_model_version_1/mnist_model_version_1_0.pth", "prov:activity": "prov-ml:ModelRegistration"}, "_:id84": {"prov:entity": "prov/MetricsType.ZARR_False_blosc_zstd_0/artifacts/mnist_model_version_2/mnist_model_version_2_0.pth", "prov:activity": "prov-ml:ModelRegistration"}, "_:id85": {"prov:entity": "prov/MetricsType.ZARR_False_blosc_zstd_0/artifacts/mnist_model_version_3/mnist_model_version_3_0.pth", "prov:activity": "prov-ml:ModelRegistration"}, "_:id86": {"prov:entity": "prov/MetricsType.ZARR_False_blosc_zstd_0/artifacts/mnist_model_version_4/mnist_model_version_4_0.pth", "prov:activity": "prov-ml:ModelRegistration"}, "_:id87": {"prov:entity": "prov/MetricsType.ZARR_False_blosc_zstd_0/artifacts/mnist_model_final/mnist_model_final_0.pth", "prov:activity": "prov-ml:ModelRegistration"}, "prov/MetricsType.ZARR_False_blosc_zstd_0/artifacts/metrics/MSE_train_Context.TRAINING_GR0.zarr_gen": {"prov:entity": "prov/MetricsType.ZARR_False_blosc_zstd_0/artifacts/metrics/MSE_train_Context.TRAINING_GR0.zarr", "prov:activity": "MetricsType.ZARR_False_zstd_execution"}, "prov/MetricsType.ZARR_False_blosc_zstd_0/artifacts/metrics/MSE_train2_Context.TRAINING_GR0.zarr_gen": {"prov:entity": "prov/MetricsType.ZARR_False_blosc_zstd_0/artifacts/metrics/MSE_train2_Context.TRAINING_GR0.zarr", "prov:activity": "MetricsType.ZARR_False_zstd_execution"}, "prov/MetricsType.ZARR_False_blosc_zstd_0/artifacts/metrics/MSE_train3_Context.TRAINING_GR0.zarr_gen": {"prov:entity": "prov/MetricsType.ZARR_False_blosc_zstd_0/artifacts/metrics/MSE_train3_Context.TRAINING_GR0.zarr", "prov:activity": "MetricsType.ZARR_False_zstd_execution"}, "prov/MetricsType.ZARR_False_blosc_zstd_0/artifacts/metrics/MSE_train4_Context.TRAINING_GR0.zarr_gen": {"prov:entity": "prov/MetricsType.ZARR_False_blosc_zstd_0/artifacts/metrics/MSE_train4_Context.TRAINING_GR0.zarr", "prov:activity": "MetricsType.ZARR_False_zstd_execution"}, "prov/MetricsType.ZARR_False_blosc_zstd_0/artifacts/metrics/MSE_train5_Context.TRAINING_GR0.zarr_gen": {"prov:entity": "prov/MetricsType.ZARR_False_blosc_zstd_0/artifacts/metrics/MSE_train5_Context.TRAINING_GR0.zarr", "prov:activity": "MetricsType.ZARR_False_zstd_execution"}, "prov/MetricsType.ZARR_False_blosc_zstd_0/artifacts/metrics/Indices_Context.TRAINING_GR0.zarr_gen": {"prov:entity": "prov/MetricsType.ZARR_False_blosc_zstd_0/artifacts/metrics/Indices_Context.TRAINING_GR0.zarr", "prov:activity": "MetricsType.ZARR_False_zstd_execution"}, "prov/MetricsType.ZARR_False_blosc_zstd_0/artifacts/metrics/Indices2_Context.TRAINING_GR0.zarr_gen": {"prov:entity": "prov/MetricsType.ZARR_False_blosc_zstd_0/artifacts/metrics/Indices2_Context.TRAINING_GR0.zarr", "prov:activity": "MetricsType.ZARR_False_zstd_execution"}, "prov/MetricsType.ZARR_False_blosc_zstd_0/artifacts/metrics/Indices3_Context.TRAINING_GR0.zarr_gen": {"prov:entity": "prov/MetricsType.ZARR_False_blosc_zstd_0/artifacts/metrics/Indices3_Context.TRAINING_GR0.zarr", "prov:activity": "MetricsType.ZARR_False_zstd_execution"}, "prov/MetricsType.ZARR_False_blosc_zstd_0/artifacts/metrics/Indices4_Context.TRAINING_GR0.zarr_gen": {"prov:entity": "prov/MetricsType.ZARR_False_blosc_zstd_0/artifacts/metrics/Indices4_Context.TRAINING_GR0.zarr", "prov:activity": "MetricsType.ZARR_False_zstd_execution"}, "prov/MetricsType.ZARR_False_blosc_zstd_0/artifacts/metrics/Indices5_Context.TRAINING_GR0.zarr_gen": {"prov:entity": "prov/MetricsType.ZARR_False_blosc_zstd_0/artifacts/metrics/Indices5_Context.TRAINING_GR0.zarr", "prov:activity": "MetricsType.ZARR_False_zstd_execution"}, "prov/MetricsType.ZARR_False_blosc_zstd_0/artifacts/metrics/MSE_test_Context.EVALUATION_GR0.zarr_gen": {"prov:entity": "prov/MetricsType.ZARR_False_blosc_zstd_0/artifacts/metrics/MSE_test_Context.EVALUATION_GR0.zarr", "prov:activity": "MetricsType.ZARR_False_zstd_execution"}, "_:id88": {"prov:entity": "prov/MetricsType.ZARR_False_blosc_zlib_0/artifacts/mnist_model_version_0/mnist_model_version_0_0.pth", "prov:activity": "prov-ml:ModelRegistration"}, "_:id89": {"prov:entity": "prov/MetricsType.ZARR_False_blosc_zlib_0/artifacts/mnist_model_version_1/mnist_model_version_1_0.pth", "prov:activity": "prov-ml:ModelRegistration"}, "_:id90": {"prov:entity": "prov/MetricsType.ZARR_False_blosc_zlib_0/artifacts/mnist_model_version_2/mnist_model_version_2_0.pth", "prov:activity": "prov-ml:ModelRegistration"}, "_:id91": {"prov:entity": "prov/MetricsType.ZARR_False_blosc_zlib_0/artifacts/mnist_model_version_3/mnist_model_version_3_0.pth", "prov:activity": "prov-ml:ModelRegistration"}, "_:id92": {"prov:entity": "prov/MetricsType.ZARR_False_blosc_zlib_0/artifacts/mnist_model_version_4/mnist_model_version_4_0.pth", "prov:activity": "prov-ml:ModelRegistration"}, "_:id93": {"prov:entity": "prov/MetricsType.ZARR_False_blosc_zlib_0/artifacts/mnist_model_final/mnist_model_final_0.pth", "prov:activity": "prov-ml:ModelRegistration"}, "prov/MetricsType.ZARR_False_blosc_zlib_0/artifacts/metrics/MSE_train_Context.TRAINING_GR0.zarr_gen": {"prov:entity": "prov/MetricsType.ZARR_False_blosc_zlib_0/artifacts/metrics/MSE_train_Context.TRAINING_GR0.zarr", "prov:activity": "MetricsType.ZARR_False_zstd_execution"}, "prov/MetricsType.ZARR_False_blosc_zlib_0/artifacts/metrics/MSE_train2_Context.TRAINING_GR0.zarr_gen": {"prov:entity": "prov/MetricsType.ZARR_False_blosc_zlib_0/artifacts/metrics/MSE_train2_Context.TRAINING_GR0.zarr", "prov:activity": "MetricsType.ZARR_False_zstd_execution"}, "prov/MetricsType.ZARR_False_blosc_zlib_0/artifacts/metrics/MSE_train3_Context.TRAINING_GR0.zarr_gen": {"prov:entity": "prov/MetricsType.ZARR_False_blosc_zlib_0/artifacts/metrics/MSE_train3_Context.TRAINING_GR0.zarr", "prov:activity": "MetricsType.ZARR_False_zstd_execution"}, "prov/MetricsType.ZARR_False_blosc_zlib_0/artifacts/metrics/MSE_train4_Context.TRAINING_GR0.zarr_gen": {"prov:entity": "prov/MetricsType.ZARR_False_blosc_zlib_0/artifacts/metrics/MSE_train4_Context.TRAINING_GR0.zarr", "prov:activity": "MetricsType.ZARR_False_zstd_execution"}, "prov/MetricsType.ZARR_False_blosc_zlib_0/artifacts/metrics/MSE_train5_Context.TRAINING_GR0.zarr_gen": {"prov:entity": "prov/MetricsType.ZARR_False_blosc_zlib_0/artifacts/metrics/MSE_train5_Context.TRAINING_GR0.zarr", "prov:activity": "MetricsType.ZARR_False_zstd_execution"}, "prov/MetricsType.ZARR_False_blosc_zlib_0/artifacts/metrics/Indices_Context.TRAINING_GR0.zarr_gen": {"prov:entity": "prov/MetricsType.ZARR_False_blosc_zlib_0/artifacts/metrics/Indices_Context.TRAINING_GR0.zarr", "prov:activity": "MetricsType.ZARR_False_zstd_execution"}, "prov/MetricsType.ZARR_False_blosc_zlib_0/artifacts/metrics/Indices2_Context.TRAINING_GR0.zarr_gen": {"prov:entity": "prov/MetricsType.ZARR_False_blosc_zlib_0/artifacts/metrics/Indices2_Context.TRAINING_GR0.zarr", "prov:activity": "MetricsType.ZARR_False_zstd_execution"}, "prov/MetricsType.ZARR_False_blosc_zlib_0/artifacts/metrics/Indices3_Context.TRAINING_GR0.zarr_gen": {"prov:entity": "prov/MetricsType.ZARR_False_blosc_zlib_0/artifacts/metrics/Indices3_Context.TRAINING_GR0.zarr", "prov:activity": "MetricsType.ZARR_False_zstd_execution"}, "prov/MetricsType.ZARR_False_blosc_zlib_0/artifacts/metrics/Indices4_Context.TRAINING_GR0.zarr_gen": {"prov:entity": "prov/MetricsType.ZARR_False_blosc_zlib_0/artifacts/metrics/Indices4_Context.TRAINING_GR0.zarr", "prov:activity": "MetricsType.ZARR_False_zstd_execution"}, "prov/MetricsType.ZARR_False_blosc_zlib_0/artifacts/metrics/Indices5_Context.TRAINING_GR0.zarr_gen": {"prov:entity": "prov/MetricsType.ZARR_False_blosc_zlib_0/artifacts/metrics/Indices5_Context.TRAINING_GR0.zarr", "prov:activity": "MetricsType.ZARR_False_zstd_execution"}, "prov/MetricsType.ZARR_False_blosc_zlib_0/artifacts/metrics/MSE_test_Context.EVALUATION_GR0.zarr_gen": {"prov:entity": "prov/MetricsType.ZARR_False_blosc_zlib_0/artifacts/metrics/MSE_test_Context.EVALUATION_GR0.zarr", "prov:activity": "MetricsType.ZARR_False_zstd_execution"}, "_:id94": {"prov:entity": "prov/MetricsType.ZARR_False_gzip_0/artifacts/mnist_model_version_0/mnist_model_version_0_0.pth", "prov:activity": "prov-ml:ModelRegistration"}, "_:id95": {"prov:entity": "prov/MetricsType.ZARR_False_gzip_0/artifacts/mnist_model_version_1/mnist_model_version_1_0.pth", "prov:activity": "prov-ml:ModelRegistration"}, "_:id96": {"prov:entity": "prov/MetricsType.ZARR_False_gzip_0/artifacts/mnist_model_version_2/mnist_model_version_2_0.pth", "prov:activity": "prov-ml:ModelRegistration"}, "_:id97": {"prov:entity": "prov/MetricsType.ZARR_False_gzip_0/artifacts/mnist_model_version_3/mnist_model_version_3_0.pth", "prov:activity": "prov-ml:ModelRegistration"}, "_:id98": {"prov:entity": "prov/MetricsType.ZARR_False_gzip_0/artifacts/mnist_model_version_4/mnist_model_version_4_0.pth", "prov:activity": "prov-ml:ModelRegistration"}, "_:id99": {"prov:entity": "prov/MetricsType.ZARR_False_gzip_0/artifacts/mnist_model_final/mnist_model_final_0.pth", "prov:activity": "prov-ml:ModelRegistration"}, "prov/MetricsType.ZARR_False_gzip_0/artifacts/metrics/MSE_train_Context.TRAINING_GR0.zarr_gen": {"prov:entity": "prov/MetricsType.ZARR_False_gzip_0/artifacts/metrics/MSE_train_Context.TRAINING_GR0.zarr", "prov:activity": "MetricsType.ZARR_False_zstd_execution"}, "prov/MetricsType.ZARR_False_gzip_0/artifacts/metrics/MSE_train2_Context.TRAINING_GR0.zarr_gen": {"prov:entity": "prov/MetricsType.ZARR_False_gzip_0/artifacts/metrics/MSE_train2_Context.TRAINING_GR0.zarr", "prov:activity": "MetricsType.ZARR_False_zstd_execution"}, "prov/MetricsType.ZARR_False_gzip_0/artifacts/metrics/MSE_train3_Context.TRAINING_GR0.zarr_gen": {"prov:entity": "prov/MetricsType.ZARR_False_gzip_0/artifacts/metrics/MSE_train3_Context.TRAINING_GR0.zarr", "prov:activity": "MetricsType.ZARR_False_zstd_execution"}, "prov/MetricsType.ZARR_False_gzip_0/artifacts/metrics/MSE_train4_Context.TRAINING_GR0.zarr_gen": {"prov:entity": "prov/MetricsType.ZARR_False_gzip_0/artifacts/metrics/MSE_train4_Context.TRAINING_GR0.zarr", "prov:activity": "MetricsType.ZARR_False_zstd_execution"}, "prov/MetricsType.ZARR_False_gzip_0/artifacts/metrics/MSE_train5_Context.TRAINING_GR0.zarr_gen": {"prov:entity": "prov/MetricsType.ZARR_False_gzip_0/artifacts/metrics/MSE_train5_Context.TRAINING_GR0.zarr", "prov:activity": "MetricsType.ZARR_False_zstd_execution"}, "prov/MetricsType.ZARR_False_gzip_0/artifacts/metrics/Indices_Context.TRAINING_GR0.zarr_gen": {"prov:entity": "prov/MetricsType.ZARR_False_gzip_0/artifacts/metrics/Indices_Context.TRAINING_GR0.zarr", "prov:activity": "MetricsType.ZARR_False_zstd_execution"}, "prov/MetricsType.ZARR_False_gzip_0/artifacts/metrics/Indices2_Context.TRAINING_GR0.zarr_gen": {"prov:entity": "prov/MetricsType.ZARR_False_gzip_0/artifacts/metrics/Indices2_Context.TRAINING_GR0.zarr", "prov:activity": "MetricsType.ZARR_False_zstd_execution"}, "prov/MetricsType.ZARR_False_gzip_0/artifacts/metrics/Indices3_Context.TRAINING_GR0.zarr_gen": {"prov:entity": "prov/MetricsType.ZARR_False_gzip_0/artifacts/metrics/Indices3_Context.TRAINING_GR0.zarr", "prov:activity": "MetricsType.ZARR_False_zstd_execution"}, "prov/MetricsType.ZARR_False_gzip_0/artifacts/metrics/Indices4_Context.TRAINING_GR0.zarr_gen": {"prov:entity": "prov/MetricsType.ZARR_False_gzip_0/artifacts/metrics/Indices4_Context.TRAINING_GR0.zarr", "prov:activity": "MetricsType.ZARR_False_zstd_execution"}, "prov/MetricsType.ZARR_False_gzip_0/artifacts/metrics/Indices5_Context.TRAINING_GR0.zarr_gen": {"prov:entity": "prov/MetricsType.ZARR_False_gzip_0/artifacts/metrics/Indices5_Context.TRAINING_GR0.zarr", "prov:activity": "MetricsType.ZARR_False_zstd_execution"}, "prov/MetricsType.ZARR_False_gzip_0/artifacts/metrics/MSE_test_Context.EVALUATION_GR0.zarr_gen": {"prov:entity": "prov/MetricsType.ZARR_False_gzip_0/artifacts/metrics/MSE_test_Context.EVALUATION_GR0.zarr", "prov:activity": "MetricsType.ZARR_False_zstd_execution"}, "_:id100": {"prov:entity": "prov/MetricsType.ZARR_False_zstd_0/artifacts/mnist_model_version_0/mnist_model_version_0_0.pth", "prov:activity": "prov-ml:ModelRegistration"}, "_:id101": {"prov:entity": "prov/MetricsType.ZARR_False_zstd_0/artifacts/mnist_model_version_1/mnist_model_version_1_0.pth", "prov:activity": "prov-ml:ModelRegistration"}, "_:id102": {"prov:entity": "prov/MetricsType.ZARR_False_zstd_0/artifacts/mnist_model_version_2/mnist_model_version_2_0.pth", "prov:activity": "prov-ml:ModelRegistration"}, "_:id103": {"prov:entity": "prov/MetricsType.ZARR_False_zstd_0/artifacts/mnist_model_version_3/mnist_model_version_3_0.pth", "prov:activity": "prov-ml:ModelRegistration"}, "_:id104": {"prov:entity": "prov/MetricsType.ZARR_False_zstd_0/artifacts/mnist_model_version_4/mnist_model_version_4_0.pth", "prov:activity": "prov-ml:ModelRegistration"}, "prov/MetricsType.ZARR_False_zstd_0/artifacts/metrics/MSE_train_Context.TRAINING_GR0.zarr_gen": {"prov:entity": "prov/MetricsType.ZARR_False_zstd_0/artifacts/metrics/MSE_train_Context.TRAINING_GR0.zarr", "prov:activity": "MetricsType.ZARR_False_zstd_execution"}, "prov/MetricsType.ZARR_False_zstd_0/artifacts/metrics/MSE_train2_Context.TRAINING_GR0.zarr_gen": {"prov:entity": "prov/MetricsType.ZARR_False_zstd_0/artifacts/metrics/MSE_train2_Context.TRAINING_GR0.zarr", "prov:activity": "MetricsType.ZARR_False_zstd_execution"}, "prov/MetricsType.ZARR_False_zstd_0/artifacts/metrics/MSE_train3_Context.TRAINING_GR0.zarr_gen": {"prov:entity": "prov/MetricsType.ZARR_False_zstd_0/artifacts/metrics/MSE_train3_Context.TRAINING_GR0.zarr", "prov:activity": "MetricsType.ZARR_False_zstd_execution"}, "prov/MetricsType.ZARR_False_zstd_0/artifacts/metrics/MSE_train4_Context.TRAINING_GR0.zarr_gen": {"prov:entity": "prov/MetricsType.ZARR_False_zstd_0/artifacts/metrics/MSE_train4_Context.TRAINING_GR0.zarr", "prov:activity": "MetricsType.ZARR_False_zstd_execution"}, "prov/MetricsType.ZARR_False_zstd_0/artifacts/metrics/MSE_train5_Context.TRAINING_GR0.zarr_gen": {"prov:entity": "prov/MetricsType.ZARR_False_zstd_0/artifacts/metrics/MSE_train5_Context.TRAINING_GR0.zarr", "prov:activity": "MetricsType.ZARR_False_zstd_execution"}, "prov/MetricsType.ZARR_False_zstd_0/artifacts/metrics/Indices_Context.TRAINING_GR0.zarr_gen": {"prov:entity": "prov/MetricsType.ZARR_False_zstd_0/artifacts/metrics/Indices_Context.TRAINING_GR0.zarr", "prov:activity": "MetricsType.ZARR_False_zstd_execution"}, "prov/MetricsType.ZARR_False_zstd_0/artifacts/metrics/Indices2_Context.TRAINING_GR0.zarr_gen": {"prov:entity": "prov/MetricsType.ZARR_False_zstd_0/artifacts/metrics/Indices2_Context.TRAINING_GR0.zarr", "prov:activity": "MetricsType.ZARR_False_zstd_execution"}, "prov/MetricsType.ZARR_False_zstd_0/artifacts/metrics/Indices3_Context.TRAINING_GR0.zarr_gen": {"prov:entity": "prov/MetricsType.ZARR_False_zstd_0/artifacts/metrics/Indices3_Context.TRAINING_GR0.zarr", "prov:activity": "MetricsType.ZARR_False_zstd_execution"}, "prov/MetricsType.ZARR_False_zstd_0/artifacts/metrics/Indices4_Context.TRAINING_GR0.zarr_gen": {"prov:entity": "prov/MetricsType.ZARR_False_zstd_0/artifacts/metrics/Indices4_Context.TRAINING_GR0.zarr", "prov:activity": "MetricsType.ZARR_False_zstd_execution"}, "prov/MetricsType.ZARR_False_zstd_0/artifacts/metrics/Indices5_Context.TRAINING_GR0.zarr_gen": {"prov:entity": "prov/MetricsType.ZARR_False_zstd_0/artifacts/metrics/Indices5_Context.TRAINING_GR0.zarr", "prov:activity": "MetricsType.ZARR_False_zstd_execution"}, "prov/MetricsType.ZARR_False_zstd_0/artifacts/metrics/MSE_test_Context.EVALUATION_GR0.zarr_gen": {"prov:entity": "prov/MetricsType.ZARR_False_zstd_0/artifacts/metrics/MSE_test_Context.EVALUATION_GR0.zarr", "prov:activity": "MetricsType.ZARR_False_zstd_execution"}}, "wasStartedBy": {"_:id5": {"prov:activity": "epoch_0", "prov:trigger": "MetricsType.ZARR_False_zstd_execution"}, "_:id6": {"prov:activity": "epoch_1", "prov:trigger": "MetricsType.ZARR_False_zstd_execution"}, "_:id7": {"prov:activity": "epoch_2", "prov:trigger": "MetricsType.ZARR_False_zstd_execution"}, "_:id8": {"prov:activity": "epoch_3", "prov:trigger": "MetricsType.ZARR_False_zstd_execution"}, "_:id9": {"prov:activity": "epoch_4", "prov:trigger": "MetricsType.ZARR_False_zstd_execution"}, "_:id10": {"prov:activity": "test", "prov:trigger": "MetricsType.ZARR_False_zstd_execution"}}, "wasInformedBy": {"_:id21": {"prov:informed": "prov-ml:ModelRegistration", "prov:informant": "MetricsType.ZARR_False_zstd_execution"}}}